[
  {
    "": "",
    "Date": "",
    "ONLY ME - Checkbox": "",
    "Expenses": "",
    "Expense name": "",
    "Remaining so far": "",
    "Income today": "",
    "Income name": "",
    "Actual remaining today": ""
  },
  {
    "": "",
    "Date": "2026-01-01",
    "ONLY ME - Checkbox": false,
    "Expenses": 500,
    "Expense name": "Wifi",
    "Remaining so far": -500,
    "Income today": 23000,
    "Income name": "",
    "Actual remaining today": 22500
  },
  {
    "": "",
    "Date": "2026-01-02",
    "ONLY ME - Checkbox": false,
    "Expenses": 2491.09,
    "Expense name": "Electric",
    "Remaining so far": 20008.91,
    "Income today": "",
    "Income name": "",
    "Actual remaining today": 20008.91
  },
  {
    "": "",
    "Date": "2026-01-03",
    "ONLY ME - Checkbox": "",
    "Expenses": 337.6,
    "Expense name": "Water",
    "Remaining so far": 19671.31,
    "Income today": "",
    "Income name": "",
    "Actual remaining today": 19671.31
  },
  {
    "": "",
    "Date": "2026-01-04",
    "ONLY ME - Checkbox": "",
    "Expenses": 2000,
    "Expense name": "Food",
    "Remaining so far": 17671.31,
    "Income today": "",
    "Income name": "",
    "Actual remaining today": 17671.31
  },
  {
    "": "",
    "Date": "2026-01-05",
    "ONLY ME - Checkbox": "",
    "Expenses": 5000,
    "Expense name": "roof",
    "Remaining so far": 12671.310000000001,
    "Income today": "",
    "Income name": "",
    "Actual remaining today": 12671.310000000001
  },
  {
    "": "",
    "Date": "2026-01-06",
    "ONLY ME - Checkbox": "",
    "Expenses": 4000,
    "Expense name": "weekly dates",
    "Remaining so far": 8671.310000000001,
    "Income today": "",
    "Income name": "",
    "Actual remaining today": 8671.310000000001
  },
  {
    "": "",
    "Date": "2026-01-07",
    "ONLY ME - Checkbox": "",
    "Expenses": "",
    "Expense name": "",
    "Remaining so far": 8671.310000000001,
    "Income today": "",
    "Income name": "",
    "Actual remaining today": 8671.310000000001
  },
  {
    "": "",
    "Date": "2026-01-08",
    "ONLY ME - Checkbox": "",
    "Expenses": "",
    "Expense name": "",
    "Remaining so far": 8671.310000000001,
    "Income today": "",
    "Income name": "",
    "Actual remaining today": 8671.310000000001
  },
  {
    "": "",
    "Date": "2026-01-09",
    "ONLY ME - Checkbox": "",
    "Expenses": "",
    "Expense name": "",
    "Remaining so far": 8671.310000000001,
    "Income today": "",
    "Income name": "",
    "Actual remaining today": 8671.310000000001
  },
  {
    "": "",
    "Date": "2026-01-10",
    "ONLY ME - Checkbox": "",
    "Expenses": "",
    "Expense name": "",
    "Remaining so far": 8671.310000000001,
    "Income today": "",
    "Income name": "",
    "Actual remaining today": 8671.310000000001
  },
  {
    "": "",
    "Date": "2026-01-11",
    "ONLY ME - Checkbox": "",
    "Expenses": "",
    "Expense name": "",
    "Remaining so far": 8671.310000000001,
    "Income today": "",
    "Income name": "",
    "Actual remaining today": 8671.310000000001
  },
  {
    "": "",
    "Date": "2026-01-12",
    "ONLY ME - Checkbox": "",
    "Expenses": "",
    "Expense name": "",
    "Remaining so far": 8671.310000000001,
    "Income today": "",
    "Income name": "",
    "Actual remaining today": 8671.310000000001
  },
  {
    "": "",
    "Date": "2026-01-13",
    "ONLY ME - Checkbox": "",
    "Expenses": 5318.15,
    "Expense name": "GPU",
    "Remaining so far": 3353.1600000000017,
    "Income today": "",
    "Income name": "",
    "Actual remaining today": 3353.1600000000017
  },
  {
    "": "",
    "Date": "2026-01-14",
    "ONLY ME - Checkbox": false,
    "Expenses": 4000,
    "Expense name": "Rent",
    "Remaining so far": -646.8399999999983,
    "Income today": "",
    "Income name": "",
    "Actual remaining today": -646.8399999999983
  },
  {
    "": "",
    "Date": "2026-01-15",
    "ONLY ME - Checkbox": false,
    "Expenses": 500,
    "Expense name": "Electric",
    "Remaining so far": -1146.8399999999983,
    "Income today": 23000,
    "Income name": "",
    "Actual remaining today": 21853.160000000003
  },
  {
    "": "",
    "Date": "2026-01-16",
    "ONLY ME - Checkbox": false,
    "Expenses": 110,
    "Expense name": "Water",
    "Remaining so far": 21743.160000000003,
    "Income today": "",
    "Income name": "",
    "Actual remaining today": 21743.160000000003
  },
  {
    "": "",
    "Date": "2026-01-17",
    "ONLY ME - Checkbox": false,
    "Expenses": 5000,
    "Expense name": "Food",
    "Remaining so far": 16743.160000000003,
    "Income today": "",
    "Income name": "",
    "Actual remaining today": 16743.160000000003
  },
  {
    "": "",
    "Date": "2026-01-18",
    "ONLY ME - Checkbox": false,
    "Expenses": 436.33,
    "Expense name": "SLoan",
    "Remaining so far": 16306.830000000004,
    "Income today": "",
    "Income name": "",
    "Actual remaining today": 16306.830000000004
  },
  {
    "": "",
    "Date": "2026-01-19",
    "ONLY ME - Checkbox": false,
    "Expenses": 2399.81,
    "Expense name": "SLoan",
    "Remaining so far": 13907.020000000004,
    "Income today": "",
    "Income name": "",
    "Actual remaining today": 13907.020000000004
  },
  {
    "": "",
    "Date": "2026-01-20",
    "ONLY ME - Checkbox": false,
    "Expenses": 2270.53,
    "Expense name": "SLoan",
    "Remaining so far": 11636.490000000003,
    "Income today": "",
    "Income name": "",
    "Actual remaining today": 11636.490000000003
  },
  {
    "": "",
    "Date": "2026-01-21",
    "ONLY ME - Checkbox": false,
    "Expenses": 1692.13,
    "Expense name": "GLoan",
    "Remaining so far": 9944.360000000004,
    "Income today": "",
    "Income name": "",
    "Actual remaining today": 9944.360000000004
  },
  {
    "": "",
    "Date": "2026-01-22",
    "ONLY ME - Checkbox": false,
    "Expenses": 3200,
    "Expense name": "Cino",
    "Remaining so far": 6744.360000000004,
    "Income today": "",
    "Income name": "",
    "Actual remaining today": 6744.360000000004
  },
  {
    "": "",
    "Date": "2026-01-23",
    "ONLY ME - Checkbox": false,
    "Expenses": 1500,
    "Expense name": "Ref",
    "Remaining so far": 5244.360000000004,
    "Income today": "",
    "Income name": "",
    "Actual remaining today": 5244.360000000004
  },
  {
    "": "",
    "Date": "2026-01-24",
    "ONLY ME - Checkbox": false,
    "Expenses": 545.41,
    "Expense name": "SLoan",
    "Remaining so far": 4698.950000000004,
    "Income today": "",
    "Income name": "",
    "Actual remaining today": 4698.950000000004
  },
  {
    "": "",
    "Date": "2026-01-25",
    "ONLY ME - Checkbox": "",
    "Expenses": "",
    "Expense name": "",
    "Remaining so far": 4698.950000000004,
    "Income today": "",
    "Income name": "",
    "Actual remaining today": 4698.950000000004
  },
  {
    "": "",
    "Date": "2026-01-26",
    "ONLY ME - Checkbox": "",
    "Expenses": "",
    "Expense name": "",
    "Remaining so far": 4698.950000000004,
    "Income today": "",
    "Income name": "",
    "Actual remaining today": 4698.950000000004
  },
  {
    "": "",
    "Date": "2026-01-27",
    "ONLY ME - Checkbox": "",
    "Expenses": "",
    "Expense name": "",
    "Remaining so far": 4698.950000000004,
    "Income today": "",
    "Income name": "",
    "Actual remaining today": 4698.950000000004
  },
  {
    "": "",
    "Date": "2026-01-28",
    "ONLY ME - Checkbox": "",
    "Expenses": "",
    "Expense name": "",
    "Remaining so far": 4698.950000000004,
    "Income today": "",
    "Income name": "",
    "Actual remaining today": 4698.950000000004
  },
  {
    "": "",
    "Date": "2026-01-29",
    "ONLY ME - Checkbox": "",
    "Expenses": "",
    "Expense name": "",
    "Remaining so far": 4698.950000000004,
    "Income today": "",
    "Income name": "",
    "Actual remaining today": 4698.950000000004
  },
  {
    "": "",
    "Date": "2026-01-30",
    "ONLY ME - Checkbox": "",
    "Expenses": "",
    "Expense name": "",
    "Remaining so far": 4698.950000000004,
    "Income today": 23000,
    "Income name": "",
    "Actual remaining today": 27698.950000000004
  },
  {
    "": 17698.950000000004,
    "Date": "2026-01-31",
    "ONLY ME - Checkbox": false,
    "Expenses": 10000,
    "Expense name": "Buds",
    "Remaining so far": 17698.950000000004,
    "Income today": "",
    "Income name": "",
    "Actual remaining today": 17698.950000000004
  },
  {
    "": "",
    "Date": "2026-02-01",
    "ONLY ME - Checkbox": false,
    "Expenses": 500,
    "Expense name": "Wifi",
    "Remaining so far": 17198.950000000004,
    "Income today": "",
    "Income name": "",
    "Actual remaining today": 17198.950000000004
  },
  {
    "": "",
    "Date": "2026-02-02",
    "ONLY ME - Checkbox": false,
    "Expenses": 5000,
    "Expense name": "Food",
    "Remaining so far": 12198.950000000004,
    "Income today": "",
    "Income name": "",
    "Actual remaining today": 12198.950000000004
  },
  {
    "": "",
    "Date": "2026-02-03",
    "ONLY ME - Checkbox": "",
    "Expenses": "",
    "Expense name": "",
    "Remaining so far": 12198.950000000004,
    "Income today": "",
    "Income name": "",
    "Actual remaining today": 12198.950000000004
  },
  {
    "": "",
    "Date": "2026-02-04",
    "ONLY ME - Checkbox": "",
    "Expenses": "",
    "Expense name": "",
    "Remaining so far": 12198.950000000004,
    "Income today": "",
    "Income name": "",
    "Actual remaining today": 12198.950000000004
  },
  {
    "": "",
    "Date": "2026-02-05",
    "ONLY ME - Checkbox": "",
    "Expenses": "",
    "Expense name": "",
    "Remaining so far": 12198.950000000004,
    "Income today": "",
    "Income name": "",
    "Actual remaining today": 12198.950000000004
  },
  {
    "": "",
    "Date": "2026-02-06",
    "ONLY ME - Checkbox": "",
    "Expenses": "",
    "Expense name": "",
    "Remaining so far": 12198.950000000004,
    "Income today": "",
    "Income name": "",
    "Actual remaining today": 12198.950000000004
  },
  {
    "": "",
    "Date": "2026-02-07",
    "ONLY ME - Checkbox": "",
    "Expenses": 4000,
    "Expense name": "weekly dates",
    "Remaining so far": 8198.950000000004,
    "Income today": "",
    "Income name": "",
    "Actual remaining today": 8198.950000000004
  },
  {
    "": "",
    "Date": "2026-02-08",
    "ONLY ME - Checkbox": "",
    "Expenses": "",
    "Expense name": "",
    "Remaining so far": 8198.950000000004,
    "Income today": "",
    "Income name": "",
    "Actual remaining today": 8198.950000000004
  },
  {
    "": "",
    "Date": "2026-02-09",
    "ONLY ME - Checkbox": "",
    "Expenses": "",
    "Expense name": "",
    "Remaining so far": 8198.950000000004,
    "Income today": "",
    "Income name": "",
    "Actual remaining today": 8198.950000000004
  },
  {
    "": "",
    "Date": "2026-02-10",
    "ONLY ME - Checkbox": "",
    "Expenses": "",
    "Expense name": "",
    "Remaining so far": 8198.950000000004,
    "Income today": "",
    "Income name": "",
    "Actual remaining today": 8198.950000000004
  },
  {
    "": "",
    "Date": "2026-02-11",
    "ONLY ME - Checkbox": "",
    "Expenses": "",
    "Expense name": "",
    "Remaining so far": 8198.950000000004,
    "Income today": "",
    "Income name": "",
    "Actual remaining today": 8198.950000000004
  },
  {
    "": "",
    "Date": "2026-02-12",
    "ONLY ME - Checkbox": "",
    "Expenses": 5318.15,
    "Expense name": "GPU",
    "Remaining so far": 2880.8000000000047,
    "Income today": "",
    "Income name": "",
    "Actual remaining today": 2880.8000000000047
  },
  {
    "": "",
    "Date": "2026-02-13",
    "ONLY ME - Checkbox": false,
    "Expenses": 11087.47,
    "Expense name": "SpayLater",
    "Remaining so far": -8206.669999999995,
    "Income today": "",
    "Income name": "",
    "Actual remaining today": -8206.669999999995
  },
  {
    "": "",
    "Date": "2026-02-14",
    "ONLY ME - Checkbox": false,
    "Expenses": 4000,
    "Expense name": "Rent",
    "Remaining so far": -12206.669999999995,
    "Income today": "",
    "Income name": "",
    "Actual remaining today": -12206.669999999995
  },
  {
    "": "",
    "Date": "2026-02-15",
    "ONLY ME - Checkbox": false,
    "Expenses": 500,
    "Expense name": "Electric",
    "Remaining so far": -12706.669999999995,
    "Income today": 23000,
    "Income name": "",
    "Actual remaining today": 10293.330000000005
  },
  {
    "": "",
    "Date": "2026-02-16",
    "ONLY ME - Checkbox": false,
    "Expenses": 110,
    "Expense name": "Water",
    "Remaining so far": 10183.330000000005,
    "Income today": "",
    "Income name": "",
    "Actual remaining today": 10183.330000000005
  },
  {
    "": "",
    "Date": "2026-02-17",
    "ONLY ME - Checkbox": false,
    "Expenses": 5000,
    "Expense name": "Food",
    "Remaining so far": 5183.330000000005,
    "Income today": "",
    "Income name": "",
    "Actual remaining today": 5183.330000000005
  },
  {
    "": "",
    "Date": "2026-02-18",
    "ONLY ME - Checkbox": false,
    "Expenses": 436.33,
    "Expense name": "SLoan",
    "Remaining so far": 4747.0000000000055,
    "Income today": "",
    "Income name": "",
    "Actual remaining today": 4747.0000000000055
  },
  {
    "": "",
    "Date": "2026-02-19",
    "ONLY ME - Checkbox": false,
    "Expenses": 2399.81,
    "Expense name": "SLoan",
    "Remaining so far": 2347.1900000000055,
    "Income today": "",
    "Income name": "",
    "Actual remaining today": 2347.1900000000055
  },
  {
    "": "",
    "Date": "2026-02-20",
    "ONLY ME - Checkbox": false,
    "Expenses": 2270.53,
    "Expense name": "SLoan",
    "Remaining so far": 76.66000000000531,
    "Income today": "",
    "Income name": "",
    "Actual remaining today": 76.66000000000531
  },
  {
    "": "",
    "Date": "2026-02-21",
    "ONLY ME - Checkbox": false,
    "Expenses": 1692.13,
    "Expense name": "GLoan",
    "Remaining so far": -1615.4699999999948,
    "Income today": "",
    "Income name": "",
    "Actual remaining today": -1615.4699999999948
  },
  {
    "": "",
    "Date": "2026-02-22",
    "ONLY ME - Checkbox": false,
    "Expenses": 3200,
    "Expense name": "Cino",
    "Remaining so far": -4815.469999999995,
    "Income today": "",
    "Income name": "",
    "Actual remaining today": -4815.469999999995
  },
  {
    "": "",
    "Date": "2026-02-23",
    "ONLY ME - Checkbox": false,
    "Expenses": 1500,
    "Expense name": "Ref",
    "Remaining so far": -6315.469999999995,
    "Income today": "",
    "Income name": "",
    "Actual remaining today": -6315.469999999995
  },
  {
    "": "",
    "Date": "2026-02-24",
    "ONLY ME - Checkbox": false,
    "Expenses": 545.41,
    "Expense name": "SLoan",
    "Remaining so far": -6860.879999999995,
    "Income today": "",
    "Income name": "",
    "Actual remaining today": -6860.879999999995
  },
  {
    "": "",
    "Date": "2026-02-25",
    "ONLY ME - Checkbox": "",
    "Expenses": "",
    "Expense name": "",
    "Remaining so far": -6860.879999999995,
    "Income today": "",
    "Income name": "",
    "Actual remaining today": -6860.879999999995
  },
  {
    "": "",
    "Date": "2026-02-26",
    "ONLY ME - Checkbox": "",
    "Expenses": "",
    "Expense name": "",
    "Remaining so far": -6860.879999999995,
    "Income today": "",
    "Income name": "",
    "Actual remaining today": -6860.879999999995
  },
  {
    "": "",
    "Date": "2026-02-27",
    "ONLY ME - Checkbox": "",
    "Expenses": "",
    "Expense name": "",
    "Remaining so far": -6860.879999999995,
    "Income today": "",
    "Income name": "",
    "Actual remaining today": -6860.879999999995
  },
  {
    "": 1139.1200000000063,
    "Date": "2026-02-28",
    "ONLY ME - Checkbox": false,
    "Expenses": 15000,
    "Expense name": "Buds",
    "Remaining so far": -21860.879999999994,
    "Income today": 23000,
    "Income name": "",
    "Actual remaining today": 1139.1200000000063
  },
  {
    "": "",
    "Date": "2026-03-01",
    "ONLY ME - Checkbox": false,
    "Expenses": 500,
    "Expense name": "Wifi",
    "Remaining so far": 639.1200000000063,
    "Income today": "",
    "Income name": "",
    "Actual remaining today": 639.1200000000063
  },
  {
    "": "",
    "Date": "2026-03-02",
    "ONLY ME - Checkbox": false,
    "Expenses": 5000,
    "Expense name": "Food",
    "Remaining so far": -4360.879999999994,
    "Income today": "",
    "Income name": "",
    "Actual remaining today": -4360.879999999994
  },
  {
    "": "",
    "Date": "2026-03-03",
    "ONLY ME - Checkbox": "",
    "Expenses": "",
    "Expense name": "",
    "Remaining so far": -4360.879999999994,
    "Income today": "",
    "Income name": "",
    "Actual remaining today": -4360.879999999994
  },
  {
    "": "",
    "Date": "2026-03-04",
    "ONLY ME - Checkbox": "",
    "Expenses": "",
    "Expense name": "",
    "Remaining so far": -4360.879999999994,
    "Income today": "",
    "Income name": "",
    "Actual remaining today": -4360.879999999994
  },
  {
    "": "",
    "Date": "2026-03-05",
    "ONLY ME - Checkbox": "",
    "Expenses": 4000,
    "Expense name": "weekly dates",
    "Remaining so far": -8360.879999999994,
    "Income today": "",
    "Income name": "",
    "Actual remaining today": -8360.879999999994
  },
  {
    "": "",
    "Date": "2026-03-06",
    "ONLY ME - Checkbox": "",
    "Expenses": "",
    "Expense name": "",
    "Remaining so far": -8360.879999999994,
    "Income today": "",
    "Income name": "",
    "Actual remaining today": -8360.879999999994
  },
  {
    "": "",
    "Date": "2026-03-07",
    "ONLY ME - Checkbox": "",
    "Expenses": "",
    "Expense name": "",
    "Remaining so far": -8360.879999999994,
    "Income today": "",
    "Income name": "",
    "Actual remaining today": -8360.879999999994
  },
  {
    "": "",
    "Date": "2026-03-08",
    "ONLY ME - Checkbox": "",
    "Expenses": "",
    "Expense name": "",
    "Remaining so far": -8360.879999999994,
    "Income today": "",
    "Income name": "",
    "Actual remaining today": -8360.879999999994
  },
  {
    "": "",
    "Date": "2026-03-09",
    "ONLY ME - Checkbox": "",
    "Expenses": "",
    "Expense name": "",
    "Remaining so far": -8360.879999999994,
    "Income today": "",
    "Income name": "",
    "Actual remaining today": -8360.879999999994
  },
  {
    "": "",
    "Date": "2026-03-10",
    "ONLY ME - Checkbox": "",
    "Expenses": "",
    "Expense name": "",
    "Remaining so far": -8360.879999999994,
    "Income today": "",
    "Income name": "",
    "Actual remaining today": -8360.879999999994
  },
  {
    "": "",
    "Date": "2026-03-11",
    "ONLY ME - Checkbox": "",
    "Expenses": "",
    "Expense name": "",
    "Remaining so far": -8360.879999999994,
    "Income today": "",
    "Income name": "",
    "Actual remaining today": -8360.879999999994
  },
  {
    "": "",
    "Date": "2026-03-12",
    "ONLY ME - Checkbox": "",
    "Expenses": 5318.15,
    "Expense name": "GPU",
    "Remaining so far": -13679.029999999993,
    "Income today": "",
    "Income name": "",
    "Actual remaining today": -13679.029999999993
  },
  {
    "": "",
    "Date": "2026-03-13",
    "ONLY ME - Checkbox": false,
    "Expenses": 2864.05,
    "Expense name": "SpayLater",
    "Remaining so far": -16543.079999999994,
    "Income today": "",
    "Income name": "",
    "Actual remaining today": -16543.079999999994
  },
  {
    "": "",
    "Date": "2026-03-14",
    "ONLY ME - Checkbox": false,
    "Expenses": 4000,
    "Expense name": "Rent",
    "Remaining so far": -20543.079999999994,
    "Income today": "",
    "Income name": "",
    "Actual remaining today": -20543.079999999994
  },
  {
    "": "",
    "Date": "2026-03-15",
    "ONLY ME - Checkbox": false,
    "Expenses": 500,
    "Expense name": "Electric",
    "Remaining so far": -21043.079999999994,
    "Income today": 23000,
    "Income name": "",
    "Actual remaining today": 1956.9200000000055
  },
  {
    "": "",
    "Date": "2026-03-16",
    "ONLY ME - Checkbox": false,
    "Expenses": 110,
    "Expense name": "Water",
    "Remaining so far": 1846.9200000000055,
    "Income today": "",
    "Income name": "",
    "Actual remaining today": 1846.9200000000055
  },
  {
    "": "",
    "Date": "2026-03-17",
    "ONLY ME - Checkbox": false,
    "Expenses": 5000,
    "Expense name": "Food",
    "Remaining so far": -3153.0799999999945,
    "Income today": "",
    "Income name": "",
    "Actual remaining today": -3153.0799999999945
  },
  {
    "": "",
    "Date": "2026-03-18",
    "ONLY ME - Checkbox": false,
    "Expenses": 2399.81,
    "Expense name": "SLoan",
    "Remaining so far": -5552.889999999994,
    "Income today": "",
    "Income name": "",
    "Actual remaining today": -5552.889999999994
  },
  {
    "": "",
    "Date": "2026-03-19",
    "ONLY ME - Checkbox": "",
    "Expenses": "",
    "Expense name": "",
    "Remaining so far": -5552.889999999994,
    "Income today": "",
    "Income name": "",
    "Actual remaining today": -5552.889999999994
  },
  {
    "": "",
    "Date": "2026-03-20",
    "ONLY ME - Checkbox": "",
    "Expenses": "",
    "Expense name": "",
    "Remaining so far": -5552.889999999994,
    "Income today": "",
    "Income name": "",
    "Actual remaining today": -5552.889999999994
  },
  {
    "": "",
    "Date": "2026-03-21",
    "ONLY ME - Checkbox": false,
    "Expenses": 1692.13,
    "Expense name": "GLoan",
    "Remaining so far": -7245.019999999994,
    "Income today": "",
    "Income name": "",
    "Actual remaining today": -7245.019999999994
  },
  {
    "": "",
    "Date": "2026-03-22",
    "ONLY ME - Checkbox": false,
    "Expenses": 3200,
    "Expense name": "Cino",
    "Remaining so far": -10445.019999999993,
    "Income today": "",
    "Income name": "",
    "Actual remaining today": -10445.019999999993
  },
  {
    "": "",
    "Date": "2026-03-23",
    "ONLY ME - Checkbox": false,
    "Expenses": 1500,
    "Expense name": "Ref",
    "Remaining so far": -11945.019999999993,
    "Income today": "",
    "Income name": "",
    "Actual remaining today": -11945.019999999993
  },
  {
    "": "",
    "Date": "2026-03-24",
    "ONLY ME - Checkbox": false,
    "Expenses": 545.41,
    "Expense name": "SLoan",
    "Remaining so far": -12490.429999999993,
    "Income today": "",
    "Income name": "",
    "Actual remaining today": -12490.429999999993
  },
  {
    "": "",
    "Date": "2026-03-25",
    "ONLY ME - Checkbox": "",
    "Expenses": "",
    "Expense name": "",
    "Remaining so far": -12490.429999999993,
    "Income today": "",
    "Income name": "",
    "Actual remaining today": -12490.429999999993
  },
  {
    "": "",
    "Date": "2026-03-26",
    "ONLY ME - Checkbox": "",
    "Expenses": "",
    "Expense name": "",
    "Remaining so far": -12490.429999999993,
    "Income today": "",
    "Income name": "",
    "Actual remaining today": -12490.429999999993
  },
  {
    "": "",
    "Date": "2026-03-27",
    "ONLY ME - Checkbox": "",
    "Expenses": "",
    "Expense name": "",
    "Remaining so far": -12490.429999999993,
    "Income today": "",
    "Income name": "",
    "Actual remaining today": -12490.429999999993
  },
  {
    "": "",
    "Date": "2026-03-28",
    "ONLY ME - Checkbox": "",
    "Expenses": "",
    "Expense name": "",
    "Remaining so far": -12490.429999999993,
    "Income today": "",
    "Income name": "",
    "Actual remaining today": -12490.429999999993
  },
  {
    "": "",
    "Date": "2026-03-29",
    "ONLY ME - Checkbox": "",
    "Expenses": "",
    "Expense name": "",
    "Remaining so far": -12490.429999999993,
    "Income today": "",
    "Income name": "",
    "Actual remaining today": -12490.429999999993
  },
  {
    "": "",
    "Date": "2026-03-30",
    "ONLY ME - Checkbox": "",
    "Expenses": "",
    "Expense name": "",
    "Remaining so far": -12490.429999999993,
    "Income today": 23000,
    "Income name": "",
    "Actual remaining today": 10509.570000000007
  },
  {
    "": -4490.429999999993,
    "Date": "2026-03-31",
    "ONLY ME - Checkbox": false,
    "Expenses": 15000,
    "Expense name": "Buds",
    "Remaining so far": -4490.429999999993,
    "Income today": "",
    "Income name": "",
    "Actual remaining today": -4490.429999999993
  },
  {
    "": "",
    "Date": "2026-04-01",
    "ONLY ME - Checkbox": false,
    "Expenses": 500,
    "Expense name": "Wifi",
    "Remaining so far": -4990.429999999993,
    "Income today": "",
    "Income name": "",
    "Actual remaining today": -4990.429999999993
  },
  {
    "": "",
    "Date": "2026-04-02",
    "ONLY ME - Checkbox": false,
    "Expenses": 5000,
    "Expense name": "Food",
    "Remaining so far": -9990.429999999993,
    "Income today": "",
    "Income name": "",
    "Actual remaining today": -9990.429999999993
  },
  {
    "": "",
    "Date": "2026-04-03",
    "ONLY ME - Checkbox": "",
    "Expenses": "",
    "Expense name": "",
    "Remaining so far": -9990.429999999993,
    "Income today": "",
    "Income name": "",
    "Actual remaining today": -9990.429999999993
  },
  {
    "": "",
    "Date": "2026-04-04",
    "ONLY ME - Checkbox": "",
    "Expenses": "",
    "Expense name": "",
    "Remaining so far": -9990.429999999993,
    "Income today": "",
    "Income name": "",
    "Actual remaining today": -9990.429999999993
  },
  {
    "": "",
    "Date": "2026-04-05",
    "ONLY ME - Checkbox": "",
    "Expenses": 4000,
    "Expense name": "weekly dates",
    "Remaining so far": -13990.429999999993,
    "Income today": "",
    "Income name": "",
    "Actual remaining today": -13990.429999999993
  },
  {
    "": "",
    "Date": "2026-04-06",
    "ONLY ME - Checkbox": "",
    "Expenses": "",
    "Expense name": "",
    "Remaining so far": -13990.429999999993,
    "Income today": "",
    "Income name": "",
    "Actual remaining today": -13990.429999999993
  },
  {
    "": "",
    "Date": "2026-04-07",
    "ONLY ME - Checkbox": "",
    "Expenses": "",
    "Expense name": "",
    "Remaining so far": -13990.429999999993,
    "Income today": "",
    "Income name": "",
    "Actual remaining today": -13990.429999999993
  },
  {
    "": "",
    "Date": "2026-04-08",
    "ONLY ME - Checkbox": "",
    "Expenses": "",
    "Expense name": "",
    "Remaining so far": -13990.429999999993,
    "Income today": "",
    "Income name": "",
    "Actual remaining today": -13990.429999999993
  },
  {
    "": "",
    "Date": "2026-04-09",
    "ONLY ME - Checkbox": "",
    "Expenses": "",
    "Expense name": "",
    "Remaining so far": -13990.429999999993,
    "Income today": "",
    "Income name": "",
    "Actual remaining today": -13990.429999999993
  },
  {
    "": "",
    "Date": "2026-04-10",
    "ONLY ME - Checkbox": "",
    "Expenses": "",
    "Expense name": "",
    "Remaining so far": -13990.429999999993,
    "Income today": "",
    "Income name": "",
    "Actual remaining today": -13990.429999999993
  },
  {
    "": "",
    "Date": "2026-04-11",
    "ONLY ME - Checkbox": "",
    "Expenses": "",
    "Expense name": "",
    "Remaining so far": -13990.429999999993,
    "Income today": "",
    "Income name": "",
    "Actual remaining today": -13990.429999999993
  },
  {
    "": "",
    "Date": "2026-04-12",
    "ONLY ME - Checkbox": "",
    "Expenses": 5318.15,
    "Expense name": "GPU",
    "Remaining so far": -19308.579999999994,
    "Income today": "",
    "Income name": "",
    "Actual remaining today": -19308.579999999994
  },
  {
    "": "",
    "Date": "2026-04-13",
    "ONLY ME - Checkbox": false,
    "Expenses": 2790.79,
    "Expense name": "SpayLater",
    "Remaining so far": -22099.369999999995,
    "Income today": "",
    "Income name": "",
    "Actual remaining today": -22099.369999999995
  },
  {
    "": "",
    "Date": "2026-04-14",
    "ONLY ME - Checkbox": false,
    "Expenses": 4000,
    "Expense name": "Rent",
    "Remaining so far": -26099.369999999995,
    "Income today": "",
    "Income name": "",
    "Actual remaining today": -26099.369999999995
  },
  {
    "": "",
    "Date": "2026-04-15",
    "ONLY ME - Checkbox": false,
    "Expenses": 500,
    "Expense name": "Electric",
    "Remaining so far": -26599.369999999995,
    "Income today": 23000,
    "Income name": "",
    "Actual remaining today": -3599.3699999999953
  },
  {
    "": "",
    "Date": "2026-04-16",
    "ONLY ME - Checkbox": false,
    "Expenses": 110,
    "Expense name": "Water",
    "Remaining so far": -3709.3699999999953,
    "Income today": "",
    "Income name": "",
    "Actual remaining today": -3709.3699999999953
  },
  {
    "": "",
    "Date": "2026-04-17",
    "ONLY ME - Checkbox": false,
    "Expenses": 5000,
    "Expense name": "Food",
    "Remaining so far": -8709.369999999995,
    "Income today": "",
    "Income name": "",
    "Actual remaining today": -8709.369999999995
  },
  {
    "": "",
    "Date": "2026-04-18",
    "ONLY ME - Checkbox": false,
    "Expenses": 2399.81,
    "Expense name": "SLoan",
    "Remaining so far": -11109.179999999995,
    "Income today": "",
    "Income name": "",
    "Actual remaining today": -11109.179999999995
  },
  {
    "": "",
    "Date": "2026-04-19",
    "ONLY ME - Checkbox": "",
    "Expenses": "",
    "Expense name": "",
    "Remaining so far": -11109.179999999995,
    "Income today": "",
    "Income name": "",
    "Actual remaining today": -11109.179999999995
  },
  {
    "": "",
    "Date": "2026-04-20",
    "ONLY ME - Checkbox": "",
    "Expenses": "",
    "Expense name": "",
    "Remaining so far": -11109.179999999995,
    "Income today": "",
    "Income name": "",
    "Actual remaining today": -11109.179999999995
  },
  {
    "": "",
    "Date": "2026-04-21",
    "ONLY ME - Checkbox": false,
    "Expenses": 1692.13,
    "Expense name": "GLoan",
    "Remaining so far": -12801.309999999994,
    "Income today": "",
    "Income name": "",
    "Actual remaining today": -12801.309999999994
  },
  {
    "": "",
    "Date": "2026-04-22",
    "ONLY ME - Checkbox": false,
    "Expenses": 3200,
    "Expense name": "Cino",
    "Remaining so far": -16001.309999999994,
    "Income today": "",
    "Income name": "",
    "Actual remaining today": -16001.309999999994
  },
  {
    "": "",
    "Date": "2026-04-23",
    "ONLY ME - Checkbox": false,
    "Expenses": 1500,
    "Expense name": "Ref",
    "Remaining so far": -17501.309999999994,
    "Income today": "",
    "Income name": "",
    "Actual remaining today": -17501.309999999994
  },
  {
    "": "",
    "Date": "2026-04-24",
    "ONLY ME - Checkbox": "",
    "Expenses": "",
    "Expense name": "",
    "Remaining so far": -17501.309999999994,
    "Income today": "",
    "Income name": "",
    "Actual remaining today": -17501.309999999994
  },
  {
    "": "",
    "Date": "2026-04-25",
    "ONLY ME - Checkbox": "",
    "Expenses": "",
    "Expense name": "",
    "Remaining so far": -17501.309999999994,
    "Income today": "",
    "Income name": "",
    "Actual remaining today": -17501.309999999994
  },
  {
    "": "",
    "Date": "2026-04-26",
    "ONLY ME - Checkbox": "",
    "Expenses": "",
    "Expense name": "",
    "Remaining so far": -17501.309999999994,
    "Income today": "",
    "Income name": "",
    "Actual remaining today": -17501.309999999994
  },
  {
    "": "",
    "Date": "2026-04-27",
    "ONLY ME - Checkbox": "",
    "Expenses": "",
    "Expense name": "",
    "Remaining so far": -17501.309999999994,
    "Income today": "",
    "Income name": "",
    "Actual remaining today": -17501.309999999994
  },
  {
    "": "",
    "Date": "2026-04-28",
    "ONLY ME - Checkbox": "",
    "Expenses": "",
    "Expense name": "",
    "Remaining so far": -17501.309999999994,
    "Income today": "",
    "Income name": "",
    "Actual remaining today": -17501.309999999994
  },
  {
    "": "",
    "Date": "2026-04-29",
    "ONLY ME - Checkbox": "",
    "Expenses": "",
    "Expense name": "",
    "Remaining so far": -17501.309999999994,
    "Income today": "",
    "Income name": "",
    "Actual remaining today": -17501.309999999994
  },
  {
    "": -9501.309999999994,
    "Date": "2026-04-30",
    "ONLY ME - Checkbox": false,
    "Expenses": 15000,
    "Expense name": "Buds",
    "Remaining so far": -32501.309999999994,
    "Income today": 23000,
    "Income name": "",
    "Actual remaining today": -9501.309999999994
  },
  {
    "": "",
    "Date": "2026-05-01",
    "ONLY ME - Checkbox": false,
    "Expenses": 500,
    "Expense name": "Wifi",
    "Remaining so far": -10001.309999999994,
    "Income today": "",
    "Income name": "",
    "Actual remaining today": -10001.309999999994
  },
  {
    "": "",
    "Date": "2026-05-02",
    "ONLY ME - Checkbox": false,
    "Expenses": 5000,
    "Expense name": "Food",
    "Remaining so far": -15001.309999999994,
    "Income today": "",
    "Income name": "",
    "Actual remaining today": -15001.309999999994
  },
  {
    "": "",
    "Date": "2026-05-03",
    "ONLY ME - Checkbox": "",
    "Expenses": "",
    "Expense name": "",
    "Remaining so far": -15001.309999999994,
    "Income today": "",
    "Income name": "",
    "Actual remaining today": -15001.309999999994
  },
  {
    "": "",
    "Date": "2026-05-04",
    "ONLY ME - Checkbox": "",
    "Expenses": "",
    "Expense name": "",
    "Remaining so far": -15001.309999999994,
    "Income today": "",
    "Income name": "",
    "Actual remaining today": -15001.309999999994
  },
  {
    "": "",
    "Date": "2026-05-05",
    "ONLY ME - Checkbox": "",
    "Expenses": "",
    "Expense name": "",
    "Remaining so far": -15001.309999999994,
    "Income today": "",
    "Income name": "",
    "Actual remaining today": -15001.309999999994
  },
  {
    "": "",
    "Date": "2026-05-06",
    "ONLY ME - Checkbox": "",
    "Expenses": "",
    "Expense name": "",
    "Remaining so far": -15001.309999999994,
    "Income today": "",
    "Income name": "",
    "Actual remaining today": -15001.309999999994
  },
  {
    "": "",
    "Date": "2026-05-07",
    "ONLY ME - Checkbox": "",
    "Expenses": 4000,
    "Expense name": "weekly dates",
    "Remaining so far": -19001.309999999994,
    "Income today": "",
    "Income name": "",
    "Actual remaining today": -19001.309999999994
  },
  {
    "": "",
    "Date": "2026-05-08",
    "ONLY ME - Checkbox": "",
    "Expenses": "",
    "Expense name": "",
    "Remaining so far": -19001.309999999994,
    "Income today": "",
    "Income name": "",
    "Actual remaining today": -19001.309999999994
  },
  {
    "": "",
    "Date": "2026-05-09",
    "ONLY ME - Checkbox": "",
    "Expenses": "",
    "Expense name": "",
    "Remaining so far": -19001.309999999994,
    "Income today": "",
    "Income name": "",
    "Actual remaining today": -19001.309999999994
  },
  {
    "": "",
    "Date": "2026-05-10",
    "ONLY ME - Checkbox": "",
    "Expenses": "",
    "Expense name": "",
    "Remaining so far": -19001.309999999994,
    "Income today": "",
    "Income name": "",
    "Actual remaining today": -19001.309999999994
  },
  {
    "": "",
    "Date": "2026-05-11",
    "ONLY ME - Checkbox": "",
    "Expenses": "",
    "Expense name": "",
    "Remaining so far": -19001.309999999994,
    "Income today": "",
    "Income name": "",
    "Actual remaining today": -19001.309999999994
  },
  {
    "": "",
    "Date": "2026-05-12",
    "ONLY ME - Checkbox": "",
    "Expenses": 5318.15,
    "Expense name": "GPU",
    "Remaining so far": -24319.459999999992,
    "Income today": "",
    "Income name": "",
    "Actual remaining today": -24319.459999999992
  },
  {
    "": "",
    "Date": "2026-05-13",
    "ONLY ME - Checkbox": false,
    "Expenses": 2790.79,
    "Expense name": "SpayLater",
    "Remaining so far": -27110.249999999993,
    "Income today": "",
    "Income name": "",
    "Actual remaining today": -27110.249999999993
  },
  {
    "": "",
    "Date": "2026-05-14",
    "ONLY ME - Checkbox": false,
    "Expenses": 4000,
    "Expense name": "Rent",
    "Remaining so far": -31110.249999999993,
    "Income today": "",
    "Income name": "",
    "Actual remaining today": -31110.249999999993
  },
  {
    "": "",
    "Date": "2026-05-15",
    "ONLY ME - Checkbox": false,
    "Expenses": 500,
    "Expense name": "Electric",
    "Remaining so far": -31610.249999999993,
    "Income today": 23000,
    "Income name": "",
    "Actual remaining today": -8610.249999999993
  },
  {
    "": "",
    "Date": "2026-05-16",
    "ONLY ME - Checkbox": false,
    "Expenses": 110,
    "Expense name": "Water",
    "Remaining so far": -8720.249999999993,
    "Income today": "",
    "Income name": "",
    "Actual remaining today": -8720.249999999993
  },
  {
    "": "",
    "Date": "2026-05-17",
    "ONLY ME - Checkbox": false,
    "Expenses": 5000,
    "Expense name": "Food",
    "Remaining so far": -13720.249999999993,
    "Income today": "",
    "Income name": "",
    "Actual remaining today": -13720.249999999993
  },
  {
    "": "",
    "Date": "2026-05-18",
    "ONLY ME - Checkbox": "",
    "Expenses": "",
    "Expense name": "",
    "Remaining so far": -13720.249999999993,
    "Income today": "",
    "Income name": "",
    "Actual remaining today": -13720.249999999993
  },
  {
    "": "",
    "Date": "2026-05-19",
    "ONLY ME - Checkbox": "",
    "Expenses": "",
    "Expense name": "",
    "Remaining so far": -13720.249999999993,
    "Income today": "",
    "Income name": "",
    "Actual remaining today": -13720.249999999993
  },
  {
    "": "",
    "Date": "2026-05-20",
    "ONLY ME - Checkbox": "",
    "Expenses": "",
    "Expense name": "",
    "Remaining so far": -13720.249999999993,
    "Income today": "",
    "Income name": "",
    "Actual remaining today": -13720.249999999993
  },
  {
    "": "",
    "Date": "2026-05-21",
    "ONLY ME - Checkbox": false,
    "Expenses": 1692.13,
    "Expense name": "GLoan",
    "Remaining so far": -15412.379999999994,
    "Income today": "",
    "Income name": "",
    "Actual remaining today": -15412.379999999994
  },
  {
    "": "",
    "Date": "2026-05-22",
    "ONLY ME - Checkbox": false,
    "Expenses": 3200,
    "Expense name": "Cino",
    "Remaining so far": -18612.379999999994,
    "Income today": "",
    "Income name": "",
    "Actual remaining today": -18612.379999999994
  },
  {
    "": "",
    "Date": "2026-05-23",
    "ONLY ME - Checkbox": false,
    "Expenses": 1500,
    "Expense name": "Ref",
    "Remaining so far": -20112.379999999994,
    "Income today": "",
    "Income name": "",
    "Actual remaining today": -20112.379999999994
  },
  {
    "": "",
    "Date": "2026-05-24",
    "ONLY ME - Checkbox": "",
    "Expenses": "",
    "Expense name": "",
    "Remaining so far": -20112.379999999994,
    "Income today": "",
    "Income name": "",
    "Actual remaining today": -20112.379999999994
  },
  {
    "": "",
    "Date": "2026-05-25",
    "ONLY ME - Checkbox": "",
    "Expenses": "",
    "Expense name": "",
    "Remaining so far": -20112.379999999994,
    "Income today": "",
    "Income name": "",
    "Actual remaining today": -20112.379999999994
  },
  {
    "": "",
    "Date": "2026-05-26",
    "ONLY ME - Checkbox": "",
    "Expenses": "",
    "Expense name": "",
    "Remaining so far": -20112.379999999994,
    "Income today": "",
    "Income name": "",
    "Actual remaining today": -20112.379999999994
  },
  {
    "": "",
    "Date": "2026-05-27",
    "ONLY ME - Checkbox": "",
    "Expenses": "",
    "Expense name": "",
    "Remaining so far": -20112.379999999994,
    "Income today": "",
    "Income name": "",
    "Actual remaining today": -20112.379999999994
  },
  {
    "": "",
    "Date": "2026-05-28",
    "ONLY ME - Checkbox": "",
    "Expenses": "",
    "Expense name": "",
    "Remaining so far": -20112.379999999994,
    "Income today": "",
    "Income name": "",
    "Actual remaining today": -20112.379999999994
  },
  {
    "": "",
    "Date": "2026-05-29",
    "ONLY ME - Checkbox": "",
    "Expenses": "",
    "Expense name": "",
    "Remaining so far": -20112.379999999994,
    "Income today": "",
    "Income name": "",
    "Actual remaining today": -20112.379999999994
  },
  {
    "": "",
    "Date": "2026-05-30",
    "ONLY ME - Checkbox": "",
    "Expenses": "",
    "Expense name": "",
    "Remaining so far": -20112.379999999994,
    "Income today": 23000,
    "Income name": "",
    "Actual remaining today": 2887.6200000000063
  },
  {
    "": -12112.379999999994,
    "Date": "2026-05-31",
    "ONLY ME - Checkbox": false,
    "Expenses": 15000,
    "Expense name": "Buds",
    "Remaining so far": -12112.379999999994,
    "Income today": "",
    "Income name": "",
    "Actual remaining today": -12112.379999999994
  },
  {
    "": "",
    "Date": "2026-06-01",
    "ONLY ME - Checkbox": false,
    "Expenses": 500,
    "Expense name": "Wifi",
    "Remaining so far": -12612.379999999994,
    "Income today": "",
    "Income name": "",
    "Actual remaining today": -12612.379999999994
  },
  {
    "": "",
    "Date": "2026-06-02",
    "ONLY ME - Checkbox": false,
    "Expenses": 5000,
    "Expense name": "Food",
    "Remaining so far": -17612.379999999994,
    "Income today": "",
    "Income name": "",
    "Actual remaining today": -17612.379999999994
  },
  {
    "": "",
    "Date": "2026-06-03",
    "ONLY ME - Checkbox": "",
    "Expenses": "",
    "Expense name": "",
    "Remaining so far": -17612.379999999994,
    "Income today": "",
    "Income name": "",
    "Actual remaining today": -17612.379999999994
  },
  {
    "": "",
    "Date": "2026-06-04",
    "ONLY ME - Checkbox": "",
    "Expenses": 4000,
    "Expense name": "weekly dates",
    "Remaining so far": -21612.379999999994,
    "Income today": "",
    "Income name": "",
    "Actual remaining today": -21612.379999999994
  },
  {
    "": "",
    "Date": "2026-06-05",
    "ONLY ME - Checkbox": "",
    "Expenses": "",
    "Expense name": "",
    "Remaining so far": -21612.379999999994,
    "Income today": "",
    "Income name": "",
    "Actual remaining today": -21612.379999999994
  },
  {
    "": "",
    "Date": "2026-06-06",
    "ONLY ME - Checkbox": "",
    "Expenses": "",
    "Expense name": "",
    "Remaining so far": -21612.379999999994,
    "Income today": "",
    "Income name": "",
    "Actual remaining today": -21612.379999999994
  },
  {
    "": "",
    "Date": "2026-06-07",
    "ONLY ME - Checkbox": "",
    "Expenses": "",
    "Expense name": "",
    "Remaining so far": -21612.379999999994,
    "Income today": "",
    "Income name": "",
    "Actual remaining today": -21612.379999999994
  },
  {
    "": "",
    "Date": "2026-06-08",
    "ONLY ME - Checkbox": "",
    "Expenses": "",
    "Expense name": "",
    "Remaining so far": -21612.379999999994,
    "Income today": "",
    "Income name": "",
    "Actual remaining today": -21612.379999999994
  },
  {
    "": "",
    "Date": "2026-06-09",
    "ONLY ME - Checkbox": "",
    "Expenses": "",
    "Expense name": "",
    "Remaining so far": -21612.379999999994,
    "Income today": "",
    "Income name": "",
    "Actual remaining today": -21612.379999999994
  },
  {
    "": "",
    "Date": "2026-06-10",
    "ONLY ME - Checkbox": "",
    "Expenses": "",
    "Expense name": "",
    "Remaining so far": -21612.379999999994,
    "Income today": "",
    "Income name": "",
    "Actual remaining today": -21612.379999999994
  },
  {
    "": "",
    "Date": "2026-06-11",
    "ONLY ME - Checkbox": "",
    "Expenses": "",
    "Expense name": "",
    "Remaining so far": -21612.379999999994,
    "Income today": "",
    "Income name": "",
    "Actual remaining today": -21612.379999999994
  },
  {
    "": "",
    "Date": "2026-06-12",
    "ONLY ME - Checkbox": "",
    "Expenses": 5318.15,
    "Expense name": "",
    "Remaining so far": -26930.52999999999,
    "Income today": "",
    "Income name": "",
    "Actual remaining today": -26930.52999999999
  },
  {
    "": "",
    "Date": "2026-06-13",
    "ONLY ME - Checkbox": false,
    "Expenses": 2790.79,
    "Expense name": "SpayLater",
    "Remaining so far": -29721.319999999992,
    "Income today": "",
    "Income name": "",
    "Actual remaining today": -29721.319999999992
  },
  {
    "": "",
    "Date": "2026-06-14",
    "ONLY ME - Checkbox": false,
    "Expenses": 4000,
    "Expense name": "Rent",
    "Remaining so far": -33721.31999999999,
    "Income today": "",
    "Income name": "",
    "Actual remaining today": -33721.31999999999
  },
  {
    "": "",
    "Date": "2026-06-15",
    "ONLY ME - Checkbox": false,
    "Expenses": 500,
    "Expense name": "Electric",
    "Remaining so far": -34221.31999999999,
    "Income today": 23000,
    "Income name": "",
    "Actual remaining today": -11221.319999999992
  },
  {
    "": "",
    "Date": "2026-06-16",
    "ONLY ME - Checkbox": false,
    "Expenses": 110,
    "Expense name": "Water",
    "Remaining so far": -11331.319999999992,
    "Income today": "",
    "Income name": "",
    "Actual remaining today": -11331.319999999992
  },
  {
    "": "",
    "Date": "2026-06-17",
    "ONLY ME - Checkbox": false,
    "Expenses": 5000,
    "Expense name": "Food",
    "Remaining so far": -16331.319999999992,
    "Income today": "",
    "Income name": "",
    "Actual remaining today": -16331.319999999992
  },
  {
    "": "",
    "Date": "2026-06-18",
    "ONLY ME - Checkbox": "",
    "Expenses": "",
    "Expense name": "",
    "Remaining so far": -16331.319999999992,
    "Income today": "",
    "Income name": "",
    "Actual remaining today": -16331.319999999992
  },
  {
    "": "",
    "Date": "2026-06-19",
    "ONLY ME - Checkbox": "",
    "Expenses": "",
    "Expense name": "",
    "Remaining so far": -16331.319999999992,
    "Income today": "",
    "Income name": "",
    "Actual remaining today": -16331.319999999992
  },
  {
    "": "",
    "Date": "2026-06-20",
    "ONLY ME - Checkbox": "",
    "Expenses": "",
    "Expense name": "",
    "Remaining so far": -16331.319999999992,
    "Income today": "",
    "Income name": "",
    "Actual remaining today": -16331.319999999992
  },
  {
    "": "",
    "Date": "2026-06-21",
    "ONLY ME - Checkbox": false,
    "Expenses": 1692.13,
    "Expense name": "GLoan",
    "Remaining so far": -18023.449999999993,
    "Income today": "",
    "Income name": "",
    "Actual remaining today": -18023.449999999993
  },
  {
    "": "",
    "Date": "2026-06-22",
    "ONLY ME - Checkbox": false,
    "Expenses": 3200,
    "Expense name": "Cino",
    "Remaining so far": -21223.449999999993,
    "Income today": "",
    "Income name": "",
    "Actual remaining today": -21223.449999999993
  },
  {
    "": "",
    "Date": "2026-06-23",
    "ONLY ME - Checkbox": "",
    "Expenses": "",
    "Expense name": "",
    "Remaining so far": -21223.449999999993,
    "Income today": "",
    "Income name": "",
    "Actual remaining today": -21223.449999999993
  },
  {
    "": "",
    "Date": "2026-06-24",
    "ONLY ME - Checkbox": "",
    "Expenses": "",
    "Expense name": "",
    "Remaining so far": -21223.449999999993,
    "Income today": "",
    "Income name": "",
    "Actual remaining today": -21223.449999999993
  },
  {
    "": "",
    "Date": "2026-06-25",
    "ONLY ME - Checkbox": "",
    "Expenses": "",
    "Expense name": "",
    "Remaining so far": -21223.449999999993,
    "Income today": "",
    "Income name": "",
    "Actual remaining today": -21223.449999999993
  },
  {
    "": "",
    "Date": "2026-06-26",
    "ONLY ME - Checkbox": "",
    "Expenses": "",
    "Expense name": "",
    "Remaining so far": -21223.449999999993,
    "Income today": "",
    "Income name": "",
    "Actual remaining today": -21223.449999999993
  },
  {
    "": "",
    "Date": "2026-06-27",
    "ONLY ME - Checkbox": "",
    "Expenses": "",
    "Expense name": "",
    "Remaining so far": -21223.449999999993,
    "Income today": "",
    "Income name": "",
    "Actual remaining today": -21223.449999999993
  },
  {
    "": "",
    "Date": "2026-06-28",
    "ONLY ME - Checkbox": "",
    "Expenses": "",
    "Expense name": "",
    "Remaining so far": -21223.449999999993,
    "Income today": "",
    "Income name": "",
    "Actual remaining today": -21223.449999999993
  },
  {
    "": "",
    "Date": "2026-06-29",
    "ONLY ME - Checkbox": "",
    "Expenses": "",
    "Expense name": "",
    "Remaining so far": -21223.449999999993,
    "Income today": "",
    "Income name": "",
    "Actual remaining today": -21223.449999999993
  },
  {
    "": -18223.449999999997,
    "Date": "2026-06-30",
    "ONLY ME - Checkbox": false,
    "Expenses": 20000,
    "Expense name": "Buds",
    "Remaining so far": -41223.45,
    "Income today": 23000,
    "Income name": "",
    "Actual remaining today": -18223.449999999997
  },
  {
    "": "",
    "Date": "2026-07-01",
    "ONLY ME - Checkbox": false,
    "Expenses": 500,
    "Expense name": "Wifi",
    "Remaining so far": -18723.449999999997,
    "Income today": "",
    "Income name": "",
    "Actual remaining today": -18723.449999999997
  },
  {
    "": "",
    "Date": "2026-07-02",
    "ONLY ME - Checkbox": false,
    "Expenses": 5000,
    "Expense name": "Food",
    "Remaining so far": -23723.449999999997,
    "Income today": "",
    "Income name": "",
    "Actual remaining today": -23723.449999999997
  },
  {
    "": "",
    "Date": "2026-07-03",
    "ONLY ME - Checkbox": "",
    "Expenses": "",
    "Expense name": "",
    "Remaining so far": -23723.449999999997,
    "Income today": "",
    "Income name": "",
    "Actual remaining today": -23723.449999999997
  },
  {
    "": "",
    "Date": "2026-07-04",
    "ONLY ME - Checkbox": "",
    "Expenses": "",
    "Expense name": "",
    "Remaining so far": -23723.449999999997,
    "Income today": "",
    "Income name": "",
    "Actual remaining today": -23723.449999999997
  },
  {
    "": "",
    "Date": "2026-07-05",
    "ONLY ME - Checkbox": "",
    "Expenses": "",
    "Expense name": "",
    "Remaining so far": -23723.449999999997,
    "Income today": "",
    "Income name": "",
    "Actual remaining today": -23723.449999999997
  },
  {
    "": "",
    "Date": "2026-07-06",
    "ONLY ME - Checkbox": "",
    "Expenses": 4000,
    "Expense name": "weekly dates",
    "Remaining so far": -27723.449999999997,
    "Income today": "",
    "Income name": "",
    "Actual remaining today": -27723.449999999997
  },
  {
    "": "",
    "Date": "2026-07-07",
    "ONLY ME - Checkbox": "",
    "Expenses": "",
    "Expense name": "",
    "Remaining so far": -27723.449999999997,
    "Income today": "",
    "Income name": "",
    "Actual remaining today": -27723.449999999997
  },
  {
    "": "",
    "Date": "2026-07-08",
    "ONLY ME - Checkbox": "",
    "Expenses": "",
    "Expense name": "",
    "Remaining so far": -27723.449999999997,
    "Income today": "",
    "Income name": "",
    "Actual remaining today": -27723.449999999997
  },
  {
    "": "",
    "Date": "2026-07-09",
    "ONLY ME - Checkbox": "",
    "Expenses": "",
    "Expense name": "",
    "Remaining so far": -27723.449999999997,
    "Income today": "",
    "Income name": "",
    "Actual remaining today": -27723.449999999997
  },
  {
    "": "",
    "Date": "2026-07-10",
    "ONLY ME - Checkbox": "",
    "Expenses": "",
    "Expense name": "",
    "Remaining so far": -27723.449999999997,
    "Income today": "",
    "Income name": "",
    "Actual remaining today": -27723.449999999997
  },
  {
    "": "",
    "Date": "2026-07-11",
    "ONLY ME - Checkbox": "",
    "Expenses": "",
    "Expense name": "",
    "Remaining so far": -27723.449999999997,
    "Income today": "",
    "Income name": "",
    "Actual remaining today": -27723.449999999997
  },
  {
    "": "",
    "Date": "2026-07-12",
    "ONLY ME - Checkbox": "",
    "Expenses": "",
    "Expense name": "",
    "Remaining so far": -27723.449999999997,
    "Income today": "",
    "Income name": "",
    "Actual remaining today": -27723.449999999997
  },
  {
    "": "",
    "Date": "2026-07-13",
    "ONLY ME - Checkbox": false,
    "Expenses": 2790.79,
    "Expense name": "SpayLater",
    "Remaining so far": -30514.239999999998,
    "Income today": "",
    "Income name": "",
    "Actual remaining today": -30514.239999999998
  },
  {
    "": "",
    "Date": "2026-07-14",
    "ONLY ME - Checkbox": false,
    "Expenses": 4000,
    "Expense name": "Rent",
    "Remaining so far": -34514.24,
    "Income today": "",
    "Income name": "",
    "Actual remaining today": -34514.24
  },
  {
    "": "",
    "Date": "2026-07-15",
    "ONLY ME - Checkbox": false,
    "Expenses": 500,
    "Expense name": "Electric",
    "Remaining so far": -35014.24,
    "Income today": 23000,
    "Income name": "",
    "Actual remaining today": -12014.239999999998
  },
  {
    "": "",
    "Date": "2026-07-16",
    "ONLY ME - Checkbox": false,
    "Expenses": 110,
    "Expense name": "Water",
    "Remaining so far": -12124.239999999998,
    "Income today": "",
    "Income name": "",
    "Actual remaining today": -12124.239999999998
  },
  {
    "": "",
    "Date": "2026-07-17",
    "ONLY ME - Checkbox": false,
    "Expenses": 5000,
    "Expense name": "Food",
    "Remaining so far": -17124.239999999998,
    "Income today": "",
    "Income name": "",
    "Actual remaining today": -17124.239999999998
  },
  {
    "": "",
    "Date": "2026-07-18",
    "ONLY ME - Checkbox": "",
    "Expenses": "",
    "Expense name": "",
    "Remaining so far": -17124.239999999998,
    "Income today": "",
    "Income name": "",
    "Actual remaining today": -17124.239999999998
  },
  {
    "": "",
    "Date": "2026-07-19",
    "ONLY ME - Checkbox": "",
    "Expenses": "",
    "Expense name": "",
    "Remaining so far": -17124.239999999998,
    "Income today": "",
    "Income name": "",
    "Actual remaining today": -17124.239999999998
  },
  {
    "": "",
    "Date": "2026-07-20",
    "ONLY ME - Checkbox": "",
    "Expenses": "",
    "Expense name": "",
    "Remaining so far": -17124.239999999998,
    "Income today": "",
    "Income name": "",
    "Actual remaining today": -17124.239999999998
  },
  {
    "": "",
    "Date": "2026-07-21",
    "ONLY ME - Checkbox": "",
    "Expenses": "",
    "Expense name": "",
    "Remaining so far": -17124.239999999998,
    "Income today": "",
    "Income name": "",
    "Actual remaining today": -17124.239999999998
  },
  {
    "": "",
    "Date": "2026-07-22",
    "ONLY ME - Checkbox": false,
    "Expenses": 3200,
    "Expense name": "Cino",
    "Remaining so far": -20324.239999999998,
    "Income today": "",
    "Income name": "",
    "Actual remaining today": -20324.239999999998
  },
  {
    "": "",
    "Date": "2026-07-23",
    "ONLY ME - Checkbox": "",
    "Expenses": "",
    "Expense name": "",
    "Remaining so far": -20324.239999999998,
    "Income today": "",
    "Income name": "",
    "Actual remaining today": -20324.239999999998
  },
  {
    "": "",
    "Date": "2026-07-24",
    "ONLY ME - Checkbox": "",
    "Expenses": "",
    "Expense name": "",
    "Remaining so far": -20324.239999999998,
    "Income today": "",
    "Income name": "",
    "Actual remaining today": -20324.239999999998
  },
  {
    "": "",
    "Date": "2026-07-25",
    "ONLY ME - Checkbox": "",
    "Expenses": "",
    "Expense name": "",
    "Remaining so far": -20324.239999999998,
    "Income today": "",
    "Income name": "",
    "Actual remaining today": -20324.239999999998
  },
  {
    "": "",
    "Date": "2026-07-26",
    "ONLY ME - Checkbox": "",
    "Expenses": "",
    "Expense name": "",
    "Remaining so far": -20324.239999999998,
    "Income today": "",
    "Income name": "",
    "Actual remaining today": -20324.239999999998
  },
  {
    "": "",
    "Date": "2026-07-27",
    "ONLY ME - Checkbox": "",
    "Expenses": "",
    "Expense name": "",
    "Remaining so far": -20324.239999999998,
    "Income today": "",
    "Income name": "",
    "Actual remaining today": -20324.239999999998
  },
  {
    "": "",
    "Date": "2026-07-28",
    "ONLY ME - Checkbox": "",
    "Expenses": "",
    "Expense name": "",
    "Remaining so far": -20324.239999999998,
    "Income today": "",
    "Income name": "",
    "Actual remaining today": -20324.239999999998
  },
  {
    "": "",
    "Date": "2026-07-29",
    "ONLY ME - Checkbox": "",
    "Expenses": "",
    "Expense name": "",
    "Remaining so far": -20324.239999999998,
    "Income today": "",
    "Income name": "",
    "Actual remaining today": -20324.239999999998
  },
  {
    "": "",
    "Date": "2026-07-30",
    "ONLY ME - Checkbox": "",
    "Expenses": "",
    "Expense name": "",
    "Remaining so far": -20324.239999999998,
    "Income today": 23000,
    "Income name": "",
    "Actual remaining today": 2675.760000000002
  },
  {
    "": 2675.760000000002,
    "Date": "2026-07-31",
    "ONLY ME - Checkbox": false,
    "Expenses": "",
    "Expense name": "",
    "Remaining so far": 2675.760000000002,
    "Income today": "",
    "Income name": "",
    "Actual remaining today": 2675.760000000002
  },
  {
    "": "",
    "Date": "2026-08-01",
    "ONLY ME - Checkbox": false,
    "Expenses": 500,
    "Expense name": "Wifi",
    "Remaining so far": 2175.760000000002,
    "Income today": "",
    "Income name": "",
    "Actual remaining today": 2175.760000000002
  },
  {
    "": "",
    "Date": "2026-08-02",
    "ONLY ME - Checkbox": false,
    "Expenses": 5000,
    "Expense name": "Food",
    "Remaining so far": -2824.239999999998,
    "Income today": "",
    "Income name": "",
    "Actual remaining today": -2824.239999999998
  },
  {
    "": "",
    "Date": "2026-08-03",
    "ONLY ME - Checkbox": "",
    "Expenses": "",
    "Expense name": "",
    "Remaining so far": -2824.239999999998,
    "Income today": "",
    "Income name": "",
    "Actual remaining today": -2824.239999999998
  },
  {
    "": "",
    "Date": "2026-08-04",
    "ONLY ME - Checkbox": "",
    "Expenses": "",
    "Expense name": "",
    "Remaining so far": -2824.239999999998,
    "Income today": "",
    "Income name": "",
    "Actual remaining today": -2824.239999999998
  },
  {
    "": "",
    "Date": "2026-08-05",
    "ONLY ME - Checkbox": "",
    "Expenses": 4000,
    "Expense name": "weekly dates",
    "Remaining so far": -6824.239999999998,
    "Income today": "",
    "Income name": "",
    "Actual remaining today": -6824.239999999998
  },
  {
    "": "",
    "Date": "2026-08-06",
    "ONLY ME - Checkbox": "",
    "Expenses": "",
    "Expense name": "",
    "Remaining so far": -6824.239999999998,
    "Income today": "",
    "Income name": "",
    "Actual remaining today": -6824.239999999998
  },
  {
    "": "",
    "Date": "2026-08-07",
    "ONLY ME - Checkbox": "",
    "Expenses": "",
    "Expense name": "",
    "Remaining so far": -6824.239999999998,
    "Income today": "",
    "Income name": "",
    "Actual remaining today": -6824.239999999998
  },
  {
    "": "",
    "Date": "2026-08-08",
    "ONLY ME - Checkbox": "",
    "Expenses": "",
    "Expense name": "",
    "Remaining so far": -6824.239999999998,
    "Income today": "",
    "Income name": "",
    "Actual remaining today": -6824.239999999998
  },
  {
    "": "",
    "Date": "2026-08-09",
    "ONLY ME - Checkbox": "",
    "Expenses": "",
    "Expense name": "",
    "Remaining so far": -6824.239999999998,
    "Income today": "",
    "Income name": "",
    "Actual remaining today": -6824.239999999998
  },
  {
    "": "",
    "Date": "2026-08-10",
    "ONLY ME - Checkbox": "",
    "Expenses": "",
    "Expense name": "",
    "Remaining so far": -6824.239999999998,
    "Income today": "",
    "Income name": "",
    "Actual remaining today": -6824.239999999998
  },
  {
    "": "",
    "Date": "2026-08-11",
    "ONLY ME - Checkbox": "",
    "Expenses": "",
    "Expense name": "",
    "Remaining so far": -6824.239999999998,
    "Income today": "",
    "Income name": "",
    "Actual remaining today": -6824.239999999998
  },
  {
    "": "",
    "Date": "2026-08-12",
    "ONLY ME - Checkbox": "",
    "Expenses": "",
    "Expense name": "",
    "Remaining so far": -6824.239999999998,
    "Income today": "",
    "Income name": "",
    "Actual remaining today": -6824.239999999998
  },
  {
    "": "",
    "Date": "2026-08-13",
    "ONLY ME - Checkbox": false,
    "Expenses": 2790.79,
    "Expense name": "SpayLater",
    "Remaining so far": -9615.029999999999,
    "Income today": "",
    "Income name": "",
    "Actual remaining today": -9615.029999999999
  },
  {
    "": "",
    "Date": "2026-08-14",
    "ONLY ME - Checkbox": false,
    "Expenses": 4000,
    "Expense name": "Rent",
    "Remaining so far": -13615.029999999999,
    "Income today": "",
    "Income name": "",
    "Actual remaining today": -13615.029999999999
  },
  {
    "": "",
    "Date": "2026-08-15",
    "ONLY ME - Checkbox": false,
    "Expenses": 500,
    "Expense name": "Electric",
    "Remaining so far": -14115.029999999999,
    "Income today": 23000,
    "Income name": "",
    "Actual remaining today": 8884.970000000001
  },
  {
    "": "",
    "Date": "2026-08-16",
    "ONLY ME - Checkbox": false,
    "Expenses": 110,
    "Expense name": "Water",
    "Remaining so far": 8774.970000000001,
    "Income today": "",
    "Income name": "",
    "Actual remaining today": 8774.970000000001
  },
  {
    "": "",
    "Date": "2026-08-17",
    "ONLY ME - Checkbox": false,
    "Expenses": 5000,
    "Expense name": "Food",
    "Remaining so far": 3774.970000000001,
    "Income today": "",
    "Income name": "",
    "Actual remaining today": 3774.970000000001
  },
  {
    "": "",
    "Date": "2026-08-18",
    "ONLY ME - Checkbox": "",
    "Expenses": "",
    "Expense name": "",
    "Remaining so far": 3774.970000000001,
    "Income today": "",
    "Income name": "",
    "Actual remaining today": 3774.970000000001
  },
  {
    "": "",
    "Date": "2026-08-19",
    "ONLY ME - Checkbox": "",
    "Expenses": "",
    "Expense name": "",
    "Remaining so far": 3774.970000000001,
    "Income today": "",
    "Income name": "",
    "Actual remaining today": 3774.970000000001
  },
  {
    "": "",
    "Date": "2026-08-20",
    "ONLY ME - Checkbox": "",
    "Expenses": "",
    "Expense name": "",
    "Remaining so far": 3774.970000000001,
    "Income today": "",
    "Income name": "",
    "Actual remaining today": 3774.970000000001
  },
  {
    "": "",
    "Date": "2026-08-21",
    "ONLY ME - Checkbox": "",
    "Expenses": "",
    "Expense name": "",
    "Remaining so far": 3774.970000000001,
    "Income today": "",
    "Income name": "",
    "Actual remaining today": 3774.970000000001
  },
  {
    "": "",
    "Date": "2026-08-22",
    "ONLY ME - Checkbox": false,
    "Expenses": 3200,
    "Expense name": "Cino",
    "Remaining so far": 574.9700000000012,
    "Income today": "",
    "Income name": "",
    "Actual remaining today": 574.9700000000012
  },
  {
    "": "",
    "Date": "2026-08-23",
    "ONLY ME - Checkbox": "",
    "Expenses": "",
    "Expense name": "",
    "Remaining so far": 574.9700000000012,
    "Income today": "",
    "Income name": "",
    "Actual remaining today": 574.9700000000012
  },
  {
    "": "",
    "Date": "2026-08-24",
    "ONLY ME - Checkbox": "",
    "Expenses": "",
    "Expense name": "",
    "Remaining so far": 574.9700000000012,
    "Income today": "",
    "Income name": "",
    "Actual remaining today": 574.9700000000012
  },
  {
    "": "",
    "Date": "2026-08-25",
    "ONLY ME - Checkbox": "",
    "Expenses": "",
    "Expense name": "",
    "Remaining so far": 574.9700000000012,
    "Income today": "",
    "Income name": "",
    "Actual remaining today": 574.9700000000012
  },
  {
    "": "",
    "Date": "2026-08-26",
    "ONLY ME - Checkbox": "",
    "Expenses": "",
    "Expense name": "",
    "Remaining so far": 574.9700000000012,
    "Income today": "",
    "Income name": "",
    "Actual remaining today": 574.9700000000012
  },
  {
    "": "",
    "Date": "2026-08-27",
    "ONLY ME - Checkbox": "",
    "Expenses": "",
    "Expense name": "",
    "Remaining so far": 574.9700000000012,
    "Income today": "",
    "Income name": "",
    "Actual remaining today": 574.9700000000012
  },
  {
    "": "",
    "Date": "2026-08-28",
    "ONLY ME - Checkbox": "",
    "Expenses": "",
    "Expense name": "",
    "Remaining so far": 574.9700000000012,
    "Income today": "",
    "Income name": "",
    "Actual remaining today": 574.9700000000012
  },
  {
    "": "",
    "Date": "2026-08-29",
    "ONLY ME - Checkbox": "",
    "Expenses": "",
    "Expense name": "",
    "Remaining so far": 574.9700000000012,
    "Income today": "",
    "Income name": "",
    "Actual remaining today": 574.9700000000012
  },
  {
    "": "",
    "Date": "2026-08-30",
    "ONLY ME - Checkbox": "",
    "Expenses": "",
    "Expense name": "",
    "Remaining so far": 574.9700000000012,
    "Income today": 23000,
    "Income name": "",
    "Actual remaining today": 23574.97
  },
  {
    "": 23574.97,
    "Date": "2026-08-31",
    "ONLY ME - Checkbox": false,
    "Expenses": "",
    "Expense name": "",
    "Remaining so far": 23574.97,
    "Income today": "",
    "Income name": "",
    "Actual remaining today": 23574.97
  },
  {
    "": "",
    "Date": "2026-09-01",
    "ONLY ME - Checkbox": false,
    "Expenses": 500,
    "Expense name": "Wifi",
    "Remaining so far": 23074.97,
    "Income today": "",
    "Income name": "",
    "Actual remaining today": 23074.97
  },
  {
    "": "",
    "Date": "2026-09-02",
    "ONLY ME - Checkbox": false,
    "Expenses": 5000,
    "Expense name": "Food",
    "Remaining so far": 18074.97,
    "Income today": "",
    "Income name": "",
    "Actual remaining today": 18074.97
  },
  {
    "": "",
    "Date": "2026-09-03",
    "ONLY ME - Checkbox": "",
    "Expenses": "",
    "Expense name": "",
    "Remaining so far": 18074.97,
    "Income today": "",
    "Income name": "",
    "Actual remaining today": 18074.97
  },
  {
    "": "",
    "Date": "2026-09-04",
    "ONLY ME - Checkbox": "",
    "Expenses": "",
    "Expense name": "",
    "Remaining so far": 18074.97,
    "Income today": "",
    "Income name": "",
    "Actual remaining today": 18074.97
  },
  {
    "": "",
    "Date": "2026-09-05",
    "ONLY ME - Checkbox": "",
    "Expenses": "",
    "Expense name": "",
    "Remaining so far": 18074.97,
    "Income today": "",
    "Income name": "",
    "Actual remaining today": 18074.97
  },
  {
    "": "",
    "Date": "2026-09-06",
    "ONLY ME - Checkbox": "",
    "Expenses": 4000,
    "Expense name": "weekly dates",
    "Remaining so far": 14074.970000000001,
    "Income today": "",
    "Income name": "",
    "Actual remaining today": 14074.970000000001
  },
  {
    "": "",
    "Date": "2026-09-07",
    "ONLY ME - Checkbox": "",
    "Expenses": "",
    "Expense name": "",
    "Remaining so far": 14074.970000000001,
    "Income today": "",
    "Income name": "",
    "Actual remaining today": 14074.970000000001
  },
  {
    "": "",
    "Date": "2026-09-08",
    "ONLY ME - Checkbox": "",
    "Expenses": "",
    "Expense name": "",
    "Remaining so far": 14074.970000000001,
    "Income today": "",
    "Income name": "",
    "Actual remaining today": 14074.970000000001
  },
  {
    "": "",
    "Date": "2026-09-09",
    "ONLY ME - Checkbox": "",
    "Expenses": "",
    "Expense name": "",
    "Remaining so far": 14074.970000000001,
    "Income today": "",
    "Income name": "",
    "Actual remaining today": 14074.970000000001
  },
  {
    "": "",
    "Date": "2026-09-10",
    "ONLY ME - Checkbox": "",
    "Expenses": "",
    "Expense name": "",
    "Remaining so far": 14074.970000000001,
    "Income today": "",
    "Income name": "",
    "Actual remaining today": 14074.970000000001
  },
  {
    "": "",
    "Date": "2026-09-11",
    "ONLY ME - Checkbox": "",
    "Expenses": "",
    "Expense name": "",
    "Remaining so far": 14074.970000000001,
    "Income today": "",
    "Income name": "",
    "Actual remaining today": 14074.970000000001
  },
  {
    "": "",
    "Date": "2026-09-12",
    "ONLY ME - Checkbox": "",
    "Expenses": "",
    "Expense name": "",
    "Remaining so far": 14074.970000000001,
    "Income today": "",
    "Income name": "",
    "Actual remaining today": 14074.970000000001
  },
  {
    "": "",
    "Date": "2026-09-13",
    "ONLY ME - Checkbox": false,
    "Expenses": 2790.79,
    "Expense name": "SpayLater",
    "Remaining so far": 11284.18,
    "Income today": "",
    "Income name": "",
    "Actual remaining today": 11284.18
  },
  {
    "": "",
    "Date": "2026-09-14",
    "ONLY ME - Checkbox": false,
    "Expenses": 4000,
    "Expense name": "Rent",
    "Remaining so far": 7284.18,
    "Income today": "",
    "Income name": "",
    "Actual remaining today": 7284.18
  },
  {
    "": "",
    "Date": "2026-09-15",
    "ONLY ME - Checkbox": false,
    "Expenses": 500,
    "Expense name": "Electric",
    "Remaining so far": 6784.18,
    "Income today": 23000,
    "Income name": "",
    "Actual remaining today": 29784.18
  },
  {
    "": "",
    "Date": "2026-09-16",
    "ONLY ME - Checkbox": false,
    "Expenses": 110,
    "Expense name": "Water",
    "Remaining so far": 29674.18,
    "Income today": "",
    "Income name": "",
    "Actual remaining today": 29674.18
  },
  {
    "": "",
    "Date": "2026-09-17",
    "ONLY ME - Checkbox": false,
    "Expenses": 5000,
    "Expense name": "Food",
    "Remaining so far": 24674.18,
    "Income today": "",
    "Income name": "",
    "Actual remaining today": 24674.18
  },
  {
    "": "",
    "Date": "2026-09-18",
    "ONLY ME - Checkbox": "",
    "Expenses": "",
    "Expense name": "",
    "Remaining so far": 24674.18,
    "Income today": "",
    "Income name": "",
    "Actual remaining today": 24674.18
  },
  {
    "": "",
    "Date": "2026-09-19",
    "ONLY ME - Checkbox": "",
    "Expenses": "",
    "Expense name": "",
    "Remaining so far": 24674.18,
    "Income today": "",
    "Income name": "",
    "Actual remaining today": 24674.18
  },
  {
    "": "",
    "Date": "2026-09-20",
    "ONLY ME - Checkbox": "",
    "Expenses": "",
    "Expense name": "",
    "Remaining so far": 24674.18,
    "Income today": "",
    "Income name": "",
    "Actual remaining today": 24674.18
  },
  {
    "": "",
    "Date": "2026-09-21",
    "ONLY ME - Checkbox": "",
    "Expenses": "",
    "Expense name": "",
    "Remaining so far": 24674.18,
    "Income today": "",
    "Income name": "",
    "Actual remaining today": 24674.18
  },
  {
    "": "",
    "Date": "2026-09-22",
    "ONLY ME - Checkbox": false,
    "Expenses": 3200,
    "Expense name": "Cino",
    "Remaining so far": 21474.18,
    "Income today": "",
    "Income name": "",
    "Actual remaining today": 21474.18
  },
  {
    "": "",
    "Date": "2026-09-23",
    "ONLY ME - Checkbox": "",
    "Expenses": "",
    "Expense name": "",
    "Remaining so far": 21474.18,
    "Income today": "",
    "Income name": "",
    "Actual remaining today": 21474.18
  },
  {
    "": "",
    "Date": "2026-09-24",
    "ONLY ME - Checkbox": "",
    "Expenses": "",
    "Expense name": "",
    "Remaining so far": 21474.18,
    "Income today": "",
    "Income name": "",
    "Actual remaining today": 21474.18
  },
  {
    "": "",
    "Date": "2026-09-25",
    "ONLY ME - Checkbox": "",
    "Expenses": "",
    "Expense name": "",
    "Remaining so far": 21474.18,
    "Income today": "",
    "Income name": "",
    "Actual remaining today": 21474.18
  },
  {
    "": "",
    "Date": "2026-09-26",
    "ONLY ME - Checkbox": "",
    "Expenses": "",
    "Expense name": "",
    "Remaining so far": 21474.18,
    "Income today": "",
    "Income name": "",
    "Actual remaining today": 21474.18
  },
  {
    "": "",
    "Date": "2026-09-27",
    "ONLY ME - Checkbox": "",
    "Expenses": "",
    "Expense name": "",
    "Remaining so far": 21474.18,
    "Income today": "",
    "Income name": "",
    "Actual remaining today": 21474.18
  },
  {
    "": "",
    "Date": "2026-09-28",
    "ONLY ME - Checkbox": "",
    "Expenses": "",
    "Expense name": "",
    "Remaining so far": 21474.18,
    "Income today": "",
    "Income name": "",
    "Actual remaining today": 21474.18
  },
  {
    "": "",
    "Date": "2026-09-29",
    "ONLY ME - Checkbox": "",
    "Expenses": "",
    "Expense name": "",
    "Remaining so far": 21474.18,
    "Income today": "",
    "Income name": "",
    "Actual remaining today": 21474.18
  },
  {
    "": 44474.18,
    "Date": "2026-09-30",
    "ONLY ME - Checkbox": false,
    "Expenses": "",
    "Expense name": "",
    "Remaining so far": 21474.18,
    "Income today": 23000,
    "Income name": "",
    "Actual remaining today": 44474.18
  },
  {
    "": "Oct",
    "Date": "2026-10-01",
    "ONLY ME - Checkbox": false,
    "Expenses": 500,
    "Expense name": "Wifi",
    "Remaining so far": 43974.18,
    "Income today": "",
    "Income name": "",
    "Actual remaining today": 43974.18
  },
  {
    "": "",
    "Date": "2026-10-02",
    "ONLY ME - Checkbox": false,
    "Expenses": 5000,
    "Expense name": "Food",
    "Remaining so far": 38974.18,
    "Income today": "",
    "Income name": "",
    "Actual remaining today": 38974.18
  },
  {
    "": "",
    "Date": "2026-10-03",
    "ONLY ME - Checkbox": "",
    "Expenses": "",
    "Expense name": "",
    "Remaining so far": 38974.18,
    "Income today": "",
    "Income name": "",
    "Actual remaining today": 38974.18
  },
  {
    "": "",
    "Date": "2026-10-04",
    "ONLY ME - Checkbox": "",
    "Expenses": "",
    "Expense name": "",
    "Remaining so far": 38974.18,
    "Income today": "",
    "Income name": "",
    "Actual remaining today": 38974.18
  },
  {
    "": "",
    "Date": "2026-10-05",
    "ONLY ME - Checkbox": "",
    "Expenses": "",
    "Expense name": "",
    "Remaining so far": 38974.18,
    "Income today": "",
    "Income name": "",
    "Actual remaining today": 38974.18
  },
  {
    "": "",
    "Date": "2026-10-06",
    "ONLY ME - Checkbox": "",
    "Expenses": "",
    "Expense name": "",
    "Remaining so far": 38974.18,
    "Income today": "",
    "Income name": "",
    "Actual remaining today": 38974.18
  },
  {
    "": "",
    "Date": "2026-10-07",
    "ONLY ME - Checkbox": "",
    "Expenses": 4000,
    "Expense name": "weekly dates",
    "Remaining so far": 34974.18,
    "Income today": "",
    "Income name": "",
    "Actual remaining today": 34974.18
  },
  {
    "": "",
    "Date": "2026-10-08",
    "ONLY ME - Checkbox": "",
    "Expenses": "",
    "Expense name": "",
    "Remaining so far": 34974.18,
    "Income today": "",
    "Income name": "",
    "Actual remaining today": 34974.18
  },
  {
    "": "",
    "Date": "2026-10-09",
    "ONLY ME - Checkbox": "",
    "Expenses": "",
    "Expense name": "",
    "Remaining so far": 34974.18,
    "Income today": "",
    "Income name": "",
    "Actual remaining today": 34974.18
  },
  {
    "": "",
    "Date": "2026-10-10",
    "ONLY ME - Checkbox": "",
    "Expenses": "",
    "Expense name": "",
    "Remaining so far": 34974.18,
    "Income today": "",
    "Income name": "",
    "Actual remaining today": 34974.18
  },
  {
    "": "",
    "Date": "2026-10-11",
    "ONLY ME - Checkbox": "",
    "Expenses": "",
    "Expense name": "",
    "Remaining so far": 34974.18,
    "Income today": "",
    "Income name": "",
    "Actual remaining today": 34974.18
  },
  {
    "": "",
    "Date": "2026-10-12",
    "ONLY ME - Checkbox": "",
    "Expenses": "",
    "Expense name": "",
    "Remaining so far": 34974.18,
    "Income today": "",
    "Income name": "",
    "Actual remaining today": 34974.18
  },
  {
    "": "",
    "Date": "2026-10-13",
    "ONLY ME - Checkbox": false,
    "Expenses": 2750.08,
    "Expense name": "SpayLater",
    "Remaining so far": 32224.1,
    "Income today": "",
    "Income name": "",
    "Actual remaining today": 32224.1
  },
  {
    "": "",
    "Date": "2026-10-14",
    "ONLY ME - Checkbox": false,
    "Expenses": 4000,
    "Expense name": "Rent",
    "Remaining so far": 28224.1,
    "Income today": "",
    "Income name": "",
    "Actual remaining today": 28224.1
  },
  {
    "": "",
    "Date": "2026-10-15",
    "ONLY ME - Checkbox": false,
    "Expenses": 500,
    "Expense name": "Electric",
    "Remaining so far": 27724.1,
    "Income today": 23000,
    "Income name": "",
    "Actual remaining today": 50724.1
  },
  {
    "": "",
    "Date": "2026-10-16",
    "ONLY ME - Checkbox": false,
    "Expenses": 110,
    "Expense name": "Water",
    "Remaining so far": 50614.1,
    "Income today": "",
    "Income name": "",
    "Actual remaining today": 50614.1
  },
  {
    "": "",
    "Date": "2026-10-17",
    "ONLY ME - Checkbox": false,
    "Expenses": 5000,
    "Expense name": "Food",
    "Remaining so far": 45614.1,
    "Income today": "",
    "Income name": "",
    "Actual remaining today": 45614.1
  },
  {
    "": "",
    "Date": "2026-10-18",
    "ONLY ME - Checkbox": "",
    "Expenses": "",
    "Expense name": "",
    "Remaining so far": 45614.1,
    "Income today": "",
    "Income name": "",
    "Actual remaining today": 45614.1
  },
  {
    "": "",
    "Date": "2026-10-19",
    "ONLY ME - Checkbox": "",
    "Expenses": "",
    "Expense name": "",
    "Remaining so far": 45614.1,
    "Income today": "",
    "Income name": "",
    "Actual remaining today": 45614.1
  },
  {
    "": "",
    "Date": "2026-10-20",
    "ONLY ME - Checkbox": "",
    "Expenses": "",
    "Expense name": "",
    "Remaining so far": 45614.1,
    "Income today": "",
    "Income name": "",
    "Actual remaining today": 45614.1
  },
  {
    "": "",
    "Date": "2026-10-21",
    "ONLY ME - Checkbox": "",
    "Expenses": "",
    "Expense name": "",
    "Remaining so far": 45614.1,
    "Income today": "",
    "Income name": "",
    "Actual remaining today": 45614.1
  },
  {
    "": "",
    "Date": "2026-10-22",
    "ONLY ME - Checkbox": "",
    "Expenses": "",
    "Expense name": "",
    "Remaining so far": 45614.1,
    "Income today": "",
    "Income name": "",
    "Actual remaining today": 45614.1
  },
  {
    "": "",
    "Date": "2026-10-23",
    "ONLY ME - Checkbox": "",
    "Expenses": "",
    "Expense name": "",
    "Remaining so far": 45614.1,
    "Income today": "",
    "Income name": "",
    "Actual remaining today": 45614.1
  },
  {
    "": "",
    "Date": "2026-10-24",
    "ONLY ME - Checkbox": "",
    "Expenses": "",
    "Expense name": "",
    "Remaining so far": 45614.1,
    "Income today": "",
    "Income name": "",
    "Actual remaining today": 45614.1
  },
  {
    "": "",
    "Date": "2026-10-25",
    "ONLY ME - Checkbox": "",
    "Expenses": "",
    "Expense name": "",
    "Remaining so far": 45614.1,
    "Income today": "",
    "Income name": "",
    "Actual remaining today": 45614.1
  },
  {
    "": "",
    "Date": "2026-10-26",
    "ONLY ME - Checkbox": "",
    "Expenses": "",
    "Expense name": "",
    "Remaining so far": 45614.1,
    "Income today": "",
    "Income name": "",
    "Actual remaining today": 45614.1
  },
  {
    "": "",
    "Date": "2026-10-27",
    "ONLY ME - Checkbox": "",
    "Expenses": "",
    "Expense name": "",
    "Remaining so far": 45614.1,
    "Income today": "",
    "Income name": "",
    "Actual remaining today": 45614.1
  },
  {
    "": "",
    "Date": "2026-10-28",
    "ONLY ME - Checkbox": "",
    "Expenses": "",
    "Expense name": "",
    "Remaining so far": 45614.1,
    "Income today": "",
    "Income name": "",
    "Actual remaining today": 45614.1
  },
  {
    "": "",
    "Date": "2026-10-29",
    "ONLY ME - Checkbox": "",
    "Expenses": "",
    "Expense name": "",
    "Remaining so far": 45614.1,
    "Income today": "",
    "Income name": "",
    "Actual remaining today": 45614.1
  },
  {
    "": "",
    "Date": "2026-10-30",
    "ONLY ME - Checkbox": "",
    "Expenses": "",
    "Expense name": "",
    "Remaining so far": 45614.1,
    "Income today": 23000,
    "Income name": "",
    "Actual remaining today": 68614.1
  },
  {
    "": 68614.1,
    "Date": "2026-10-31",
    "ONLY ME - Checkbox": "",
    "Expenses": "",
    "Expense name": "",
    "Remaining so far": 68614.1,
    "Income today": "",
    "Income name": "",
    "Actual remaining today": 68614.1
  },
  {
    "": "",
    "Date": "2026-11-01",
    "ONLY ME - Checkbox": false,
    "Expenses": 500,
    "Expense name": "Wifi",
    "Remaining so far": 68114.1,
    "Income today": "",
    "Income name": "",
    "Actual remaining today": 68114.1
  },
  {
    "": "",
    "Date": "2026-11-02",
    "ONLY ME - Checkbox": false,
    "Expenses": 5000,
    "Expense name": "Food",
    "Remaining so far": 63114.100000000006,
    "Income today": "",
    "Income name": "",
    "Actual remaining today": 63114.100000000006
  },
  {
    "": "",
    "Date": "2026-11-03",
    "ONLY ME - Checkbox": "",
    "Expenses": "",
    "Expense name": "",
    "Remaining so far": 63114.100000000006,
    "Income today": "",
    "Income name": "",
    "Actual remaining today": 63114.100000000006
  },
  {
    "": "",
    "Date": "2026-11-04",
    "ONLY ME - Checkbox": "",
    "Expenses": "",
    "Expense name": "",
    "Remaining so far": 63114.100000000006,
    "Income today": "",
    "Income name": "",
    "Actual remaining today": 63114.100000000006
  },
  {
    "": "",
    "Date": "2026-11-05",
    "ONLY ME - Checkbox": "",
    "Expenses": "",
    "Expense name": "",
    "Remaining so far": 63114.100000000006,
    "Income today": "",
    "Income name": "",
    "Actual remaining today": 63114.100000000006
  },
  {
    "": "",
    "Date": "2026-11-06",
    "ONLY ME - Checkbox": "",
    "Expenses": "",
    "Expense name": "",
    "Remaining so far": 63114.100000000006,
    "Income today": "",
    "Income name": "",
    "Actual remaining today": 63114.100000000006
  },
  {
    "": "",
    "Date": "2026-11-07",
    "ONLY ME - Checkbox": "",
    "Expenses": "",
    "Expense name": "",
    "Remaining so far": 63114.100000000006,
    "Income today": "",
    "Income name": "",
    "Actual remaining today": 63114.100000000006
  },
  {
    "": "",
    "Date": "2026-11-08",
    "ONLY ME - Checkbox": "",
    "Expenses": 4000,
    "Expense name": "weekly dates",
    "Remaining so far": 59114.100000000006,
    "Income today": "",
    "Income name": "",
    "Actual remaining today": 59114.100000000006
  },
  {
    "": "",
    "Date": "2026-11-09",
    "ONLY ME - Checkbox": "",
    "Expenses": "",
    "Expense name": "",
    "Remaining so far": 59114.100000000006,
    "Income today": "",
    "Income name": "",
    "Actual remaining today": 59114.100000000006
  },
  {
    "": "",
    "Date": "2026-11-10",
    "ONLY ME - Checkbox": "",
    "Expenses": "",
    "Expense name": "",
    "Remaining so far": 59114.100000000006,
    "Income today": "",
    "Income name": "",
    "Actual remaining today": 59114.100000000006
  },
  {
    "": "",
    "Date": "2026-11-11",
    "ONLY ME - Checkbox": "",
    "Expenses": "",
    "Expense name": "",
    "Remaining so far": 59114.100000000006,
    "Income today": "",
    "Income name": "",
    "Actual remaining today": 59114.100000000006
  },
  {
    "": "",
    "Date": "2026-11-12",
    "ONLY ME - Checkbox": "",
    "Expenses": "",
    "Expense name": "",
    "Remaining so far": 59114.100000000006,
    "Income today": "",
    "Income name": "",
    "Actual remaining today": 59114.100000000006
  },
  {
    "": "",
    "Date": "2026-11-13",
    "ONLY ME - Checkbox": "",
    "Expenses": "",
    "Expense name": "",
    "Remaining so far": 59114.100000000006,
    "Income today": "",
    "Income name": "",
    "Actual remaining today": 59114.100000000006
  },
  {
    "": "",
    "Date": "2026-11-14",
    "ONLY ME - Checkbox": false,
    "Expenses": 4000,
    "Expense name": "Rent",
    "Remaining so far": 55114.100000000006,
    "Income today": "",
    "Income name": "",
    "Actual remaining today": 55114.100000000006
  },
  {
    "": "",
    "Date": "2026-11-15",
    "ONLY ME - Checkbox": false,
    "Expenses": 500,
    "Expense name": "Electric",
    "Remaining so far": 54614.100000000006,
    "Income today": 23000,
    "Income name": "",
    "Actual remaining today": 77614.1
  },
  {
    "": "",
    "Date": "2026-11-16",
    "ONLY ME - Checkbox": false,
    "Expenses": 110,
    "Expense name": "Water",
    "Remaining so far": 77504.1,
    "Income today": "",
    "Income name": "",
    "Actual remaining today": 77504.1
  },
  {
    "": "",
    "Date": "2026-11-17",
    "ONLY ME - Checkbox": false,
    "Expenses": 5000,
    "Expense name": "Food",
    "Remaining so far": 72504.1,
    "Income today": "",
    "Income name": "",
    "Actual remaining today": 72504.1
  },
  {
    "": "",
    "Date": "2026-11-18",
    "ONLY ME - Checkbox": "",
    "Expenses": "",
    "Expense name": "",
    "Remaining so far": 72504.1,
    "Income today": "",
    "Income name": "",
    "Actual remaining today": 72504.1
  },
  {
    "": "",
    "Date": "2026-11-19",
    "ONLY ME - Checkbox": "",
    "Expenses": "",
    "Expense name": "",
    "Remaining so far": 72504.1,
    "Income today": "",
    "Income name": "",
    "Actual remaining today": 72504.1
  },
  {
    "": "",
    "Date": "2026-11-20",
    "ONLY ME - Checkbox": "",
    "Expenses": "",
    "Expense name": "",
    "Remaining so far": 72504.1,
    "Income today": "",
    "Income name": "",
    "Actual remaining today": 72504.1
  },
  {
    "": "",
    "Date": "2026-11-21",
    "ONLY ME - Checkbox": "",
    "Expenses": "",
    "Expense name": "",
    "Remaining so far": 72504.1,
    "Income today": "",
    "Income name": "",
    "Actual remaining today": 72504.1
  },
  {
    "": "",
    "Date": "2026-11-22",
    "ONLY ME - Checkbox": "",
    "Expenses": "",
    "Expense name": "",
    "Remaining so far": 72504.1,
    "Income today": "",
    "Income name": "",
    "Actual remaining today": 72504.1
  },
  {
    "": "",
    "Date": "2026-11-23",
    "ONLY ME - Checkbox": "",
    "Expenses": "",
    "Expense name": "",
    "Remaining so far": 72504.1,
    "Income today": "",
    "Income name": "",
    "Actual remaining today": 72504.1
  },
  {
    "": "",
    "Date": "2026-11-24",
    "ONLY ME - Checkbox": "",
    "Expenses": "",
    "Expense name": "",
    "Remaining so far": 72504.1,
    "Income today": "",
    "Income name": "",
    "Actual remaining today": 72504.1
  },
  {
    "": "",
    "Date": "2026-11-25",
    "ONLY ME - Checkbox": "",
    "Expenses": "",
    "Expense name": "",
    "Remaining so far": 72504.1,
    "Income today": "",
    "Income name": "",
    "Actual remaining today": 72504.1
  },
  {
    "": "",
    "Date": "2026-11-26",
    "ONLY ME - Checkbox": "",
    "Expenses": "",
    "Expense name": "",
    "Remaining so far": 72504.1,
    "Income today": "",
    "Income name": "",
    "Actual remaining today": 72504.1
  },
  {
    "": "",
    "Date": "2026-11-27",
    "ONLY ME - Checkbox": "",
    "Expenses": "",
    "Expense name": "",
    "Remaining so far": 72504.1,
    "Income today": "",
    "Income name": "",
    "Actual remaining today": 72504.1
  },
  {
    "": "",
    "Date": "2026-11-28",
    "ONLY ME - Checkbox": "",
    "Expenses": "",
    "Expense name": "",
    "Remaining so far": 72504.1,
    "Income today": "",
    "Income name": "",
    "Actual remaining today": 72504.1
  },
  {
    "": "",
    "Date": "2026-11-29",
    "ONLY ME - Checkbox": "",
    "Expenses": "",
    "Expense name": "",
    "Remaining so far": 72504.1,
    "Income today": "",
    "Income name": "",
    "Actual remaining today": 72504.1
  },
  {
    "": 95504.1,
    "Date": "2026-11-30",
    "ONLY ME - Checkbox": "",
    "Expenses": "",
    "Expense name": "",
    "Remaining so far": 72504.1,
    "Income today": 23000,
    "Income name": "",
    "Actual remaining today": 95504.1
  },
  {
    "": "",
    "Date": "2026-12-01",
    "ONLY ME - Checkbox": false,
    "Expenses": 500,
    "Expense name": "Wifi",
    "Remaining so far": 95004.1,
    "Income today": "",
    "Income name": "",
    "Actual remaining today": 95004.1
  },
  {
    "": "",
    "Date": "2026-12-02",
    "ONLY ME - Checkbox": false,
    "Expenses": 5000,
    "Expense name": "Food",
    "Remaining so far": 90004.1,
    "Income today": "",
    "Income name": "",
    "Actual remaining today": 90004.1
  },
  {
    "": "",
    "Date": "2026-12-03",
    "ONLY ME - Checkbox": "",
    "Expenses": "",
    "Expense name": "",
    "Remaining so far": 90004.1,
    "Income today": "",
    "Income name": "",
    "Actual remaining today": 90004.1
  },
  {
    "": "",
    "Date": "2026-12-04",
    "ONLY ME - Checkbox": "",
    "Expenses": "",
    "Expense name": "",
    "Remaining so far": 90004.1,
    "Income today": "",
    "Income name": "",
    "Actual remaining today": 90004.1
  },
  {
    "": "",
    "Date": "2026-12-05",
    "ONLY ME - Checkbox": "",
    "Expenses": "",
    "Expense name": "",
    "Remaining so far": 90004.1,
    "Income today": "",
    "Income name": "",
    "Actual remaining today": 90004.1
  },
  {
    "": "",
    "Date": "2026-12-06",
    "ONLY ME - Checkbox": "",
    "Expenses": "",
    "Expense name": "",
    "Remaining so far": 90004.1,
    "Income today": "",
    "Income name": "",
    "Actual remaining today": 90004.1
  },
  {
    "": "",
    "Date": "2026-12-07",
    "ONLY ME - Checkbox": "",
    "Expenses": "",
    "Expense name": "",
    "Remaining so far": 90004.1,
    "Income today": "",
    "Income name": "",
    "Actual remaining today": 90004.1
  },
  {
    "": "",
    "Date": "2026-12-08",
    "ONLY ME - Checkbox": "",
    "Expenses": "",
    "Expense name": "",
    "Remaining so far": 90004.1,
    "Income today": "",
    "Income name": "",
    "Actual remaining today": 90004.1
  },
  {
    "": "",
    "Date": "2026-12-09",
    "ONLY ME - Checkbox": "",
    "Expenses": "",
    "Expense name": "",
    "Remaining so far": 90004.1,
    "Income today": "",
    "Income name": "",
    "Actual remaining today": 90004.1
  },
  {
    "": "",
    "Date": "2026-12-10",
    "ONLY ME - Checkbox": "",
    "Expenses": 4000,
    "Expense name": "weekly dates",
    "Remaining so far": 86004.1,
    "Income today": "",
    "Income name": "",
    "Actual remaining today": 86004.1
  },
  {
    "": "",
    "Date": "2026-12-11",
    "ONLY ME - Checkbox": "",
    "Expenses": "",
    "Expense name": "",
    "Remaining so far": 86004.1,
    "Income today": "",
    "Income name": "",
    "Actual remaining today": 86004.1
  },
  {
    "": "",
    "Date": "2026-12-12",
    "ONLY ME - Checkbox": "",
    "Expenses": "",
    "Expense name": "",
    "Remaining so far": 86004.1,
    "Income today": "",
    "Income name": "",
    "Actual remaining today": 86004.1
  },
  {
    "": "",
    "Date": "2026-12-13",
    "ONLY ME - Checkbox": "",
    "Expenses": "",
    "Expense name": "",
    "Remaining so far": 86004.1,
    "Income today": "",
    "Income name": "",
    "Actual remaining today": 86004.1
  },
  {
    "": "",
    "Date": "2026-12-14",
    "ONLY ME - Checkbox": false,
    "Expenses": 4000,
    "Expense name": "Rent",
    "Remaining so far": 82004.1,
    "Income today": "",
    "Income name": "",
    "Actual remaining today": 82004.1
  },
  {
    "": "",
    "Date": "2026-12-15",
    "ONLY ME - Checkbox": false,
    "Expenses": 500,
    "Expense name": "Electric",
    "Remaining so far": 81504.1,
    "Income today": 23000,
    "Income name": "",
    "Actual remaining today": 104504.1
  },
  {
    "": "",
    "Date": "2026-12-16",
    "ONLY ME - Checkbox": false,
    "Expenses": 110,
    "Expense name": "Water",
    "Remaining so far": 104394.1,
    "Income today": "",
    "Income name": "",
    "Actual remaining today": 104394.1
  },
  {
    "": "",
    "Date": "2026-12-17",
    "ONLY ME - Checkbox": false,
    "Expenses": 5000,
    "Expense name": "Food",
    "Remaining so far": 99394.1,
    "Income today": "",
    "Income name": "",
    "Actual remaining today": 99394.1
  },
  {
    "": "",
    "Date": "2026-12-18",
    "ONLY ME - Checkbox": "",
    "Expenses": "",
    "Expense name": "",
    "Remaining so far": 99394.1,
    "Income today": "",
    "Income name": "",
    "Actual remaining today": 99394.1
  },
  {
    "": "",
    "Date": "2026-12-19",
    "ONLY ME - Checkbox": "",
    "Expenses": "",
    "Expense name": "",
    "Remaining so far": 99394.1,
    "Income today": "",
    "Income name": "",
    "Actual remaining today": 99394.1
  },
  {
    "": "",
    "Date": "2026-12-20",
    "ONLY ME - Checkbox": "",
    "Expenses": "",
    "Expense name": "",
    "Remaining so far": 99394.1,
    "Income today": "",
    "Income name": "",
    "Actual remaining today": 99394.1
  },
  {
    "": "",
    "Date": "2026-12-21",
    "ONLY ME - Checkbox": "",
    "Expenses": "",
    "Expense name": "",
    "Remaining so far": 99394.1,
    "Income today": "",
    "Income name": "",
    "Actual remaining today": 99394.1
  },
  {
    "": "",
    "Date": "2026-12-22",
    "ONLY ME - Checkbox": "",
    "Expenses": "",
    "Expense name": "",
    "Remaining so far": 99394.1,
    "Income today": "",
    "Income name": "",
    "Actual remaining today": 99394.1
  },
  {
    "": "",
    "Date": "2026-12-23",
    "ONLY ME - Checkbox": "",
    "Expenses": "",
    "Expense name": "",
    "Remaining so far": 99394.1,
    "Income today": "",
    "Income name": "",
    "Actual remaining today": 99394.1
  },
  {
    "": "",
    "Date": "2026-12-24",
    "ONLY ME - Checkbox": "",
    "Expenses": "",
    "Expense name": "",
    "Remaining so far": 99394.1,
    "Income today": "",
    "Income name": "",
    "Actual remaining today": 99394.1
  },
  {
    "": "",
    "Date": "2026-12-25",
    "ONLY ME - Checkbox": "",
    "Expenses": "",
    "Expense name": "",
    "Remaining so far": 99394.1,
    "Income today": "",
    "Income name": "",
    "Actual remaining today": 99394.1
  },
  {
    "": "",
    "Date": "2026-12-26",
    "ONLY ME - Checkbox": "",
    "Expenses": "",
    "Expense name": "",
    "Remaining so far": 99394.1,
    "Income today": "",
    "Income name": "",
    "Actual remaining today": 99394.1
  },
  {
    "": "",
    "Date": "2026-12-27",
    "ONLY ME - Checkbox": "",
    "Expenses": "",
    "Expense name": "",
    "Remaining so far": 99394.1,
    "Income today": "",
    "Income name": "",
    "Actual remaining today": 99394.1
  },
  {
    "": "",
    "Date": "2026-12-28",
    "ONLY ME - Checkbox": "",
    "Expenses": "",
    "Expense name": "",
    "Remaining so far": 99394.1,
    "Income today": "",
    "Income name": "",
    "Actual remaining today": 99394.1
  },
  {
    "": "",
    "Date": "2026-12-29",
    "ONLY ME - Checkbox": "",
    "Expenses": "",
    "Expense name": "",
    "Remaining so far": 99394.1,
    "Income today": "",
    "Income name": "",
    "Actual remaining today": 99394.1
  },
  {
    "": "",
    "Date": "2026-12-30",
    "ONLY ME - Checkbox": "",
    "Expenses": "",
    "Expense name": "",
    "Remaining so far": 99394.1,
    "Income today": 23000,
    "Income name": "",
    "Actual remaining today": 122394.1
  },
  {
    "": "",
    "Date": "2026-12-31",
    "ONLY ME - Checkbox": "",
    "Expenses": "",
    "Expense name": "",
    "Remaining so far": 122394.1,
    "Income today": "",
    "Income name": "",
    "Actual remaining today": 122394.1
  }
]